basic-code/combinational-logic/and2/and2.v
// 2-input AND gate used in my programable-8-bit-microprocessor

module and2_gate(
    input       a, b,     // 2-Input
    output      y);       // Output

    // GATE PRIMATIVE
    and (y, a, b);

endmodule

module and2_dataflow(
    input       a, b,     // 2-Input
    output      y);       // Output

    // CONTINUOUS ASSIGNMENT STATEMENT
    assign y = a & b;

endmodule

module and2_behavioral(
    input       a, b,     // 2-Input
    output reg  y);       // Output

    // ALWAYS BLOCK with NON-BLOCKING PROCEDURAL ASSIGNMENT STATEMENT
    always @(a or b) begin
        y <= a & b;
    end

endmodule

basic-code/combinational-logic/and2/and2_tb.v
`timescale 1ns / 100ps // time-unit = 1 ns, precision = 100 ps

// include files are in and2.vh

module AND2_TB;

    // DATA TYPES - DECLARE REGISTERS AND WIRES (PROBES)
    reg             A, B;
    wire            Y_gate, Y_data, Y_beh;
    integer         i;

    // FOR TESTING  
    reg             TICK;
    reg [31:0]      VECTORCOUNT, ERRORS;
    reg             YEXPECTED;
    integer         FD, COUNT;
    reg [8*32-1:0]  COMMENT;

    // UNIT UNDER TEST (gate)
    and2_gate UUT_and2_gate(
        .a(A), .b(B),
        .y(Y_gate)
    );

    // UNIT UNDER TEST (dataflow)
    and2_dataflow UUT_and2_dataflow(
        .a(A), .b(B),
        .y(Y_data)
    );

    // UNIT UNDER TEST (behavioral)
    and2_behavioral UUT_and2_behavioral(
        .a(A), .b(B),
        .y(Y_beh)
    );

    // SAVE EVERYTHING FROM TOP TB MODULE IN A DUMP FILE
    initial begin
        $dumpfile("and2_tb.vcd");
        $dumpvars(0, AND2_TB);
    end

    // TICK PERIOD
    localparam TICKPERIOD = 20;

    // TICK
    always begin
        #(TICKPERIOD/2) TICK = ~TICK;
    end

    // INITIALIZE TESTBENCH
    initial begin

        // OPEN VECTOR FILE - THROW AWAY FIRST LINE
        FD=$fopen("and2_tb.tv","r");
        COUNT = $fscanf(FD, "%s", COMMENT);
        // $display ("FIRST LINE IS: %s", COMMENT);

        // INIT TESTBENCH
        COUNT = $fscanf(FD, "%s %b %b %b", COMMENT, A, B, YEXPECTED);
        TICK = 0;
        VECTORCOUNT = 1;
        ERRORS = 0;

        // DISPAY OUTPUT AND MONITOR
        $display();
        $display("TEST START --------------------------------");
        $display();
        $display("                                     GATE  DATA   BEH");
        $display("                 | TIME(ns) | A | B |  Y  |  Y  |  Y  |");
        $display("                 --------------------------------------");
        // $monitor("%4d  %10s | %8d | %1d | %1d |  %1d  |  %1d  |  %1d  |", VECTORCOUNT, COMMENT, $time, A, B, Y_gate, Y_data, Y_beh);

    end

    // APPLY TEST VECTORS ON NEG EDGE TICK (ADD DELAY)
    always @(negedge TICK) begin

        // WAIT A BIT (AFTER CHECK)
        #5;

        // GET VECTORS FROM TB FILE
        COUNT = $fscanf(FD, "%s %b %b %b", COMMENT, A, B, YEXPECTED);

        // CHECK IF EOF - PRINT SUMMARY, CLOSE VECTOR FILE AND FINISH TB
        if (COUNT == -1) begin
            $fclose(FD);
            $display();
            $display(" VECTORS: %4d", VECTORCOUNT);
            $display("  ERRORS: %4d", ERRORS);
            $display();
            $display("TEST END ----------------------------------");
            $display();
            $finish;
        end

        // GET ANOTHER VECTOR
        VECTORCOUNT = VECTORCOUNT + 1;

    end

    // CHECK TEST VECTORS ON POS EGDE TICK
    always @(posedge TICK) begin

        // WAIT A BIT
        #5;

        // DISPLAY OUTPUT ON POS EDGE TICK
        $display("%4d  %10s | %8d | %1d | %1d |  %1d  |  %1d  |  %1d  |", VECTORCOUNT, COMMENT, $time, A, B, Y_gate, Y_data, Y_beh);

        // CHECK EACH VECTOR RESULT
        if (Y_gate !== YEXPECTED) begin
            $display("***ERROR (gate) - Expected Y = %b", YEXPECTED);
            ERRORS = ERRORS + 1;
        end
        if (Y_data !== YEXPECTED) begin
            $display("***ERROR (dataflow) - Expected Y = %b", YEXPECTED);
            ERRORS = ERRORS + 1;
        end
        if (Y_beh !== YEXPECTED) begin
            $display("***ERROR (behavioral) - Expected Y = %b", YEXPECTED);
            ERRORS = ERRORS + 1;
        end

    end   

endmodule

basic-code/combinational-logic/and2/and2_tb.vcd
$date
	Sat May 20 15:54:16 2023
$end
$version
	Icarus Verilog
$end
$timescale
	100ps
$end
$scope module AND2_TB $end
$var wire 1 ! Y_gate $end
$var wire 1 " Y_data $end
$var wire 1 # Y_beh $end
$var parameter 32 $ TICKPERIOD $end
$var reg 1 % A $end
$var reg 1 & B $end
$var reg 256 ' COMMENT [255:0] $end
$var reg 32 ( ERRORS [31:0] $end
$var reg 1 ) TICK $end
$var reg 32 * VECTORCOUNT [31:0] $end
$var reg 1 + YEXPECTED $end
$var integer 32 , COUNT [31:0] $end
$var integer 32 - FD [31:0] $end
$scope module UUT_and2_behavioral $end
$var wire 1 % a $end
$var wire 1 & b $end
$var reg 1 # y $end
$upscope $end
$scope module UUT_and2_dataflow $end
$var wire 1 % a $end
$var wire 1 & b $end
$var wire 1 " y $end
$upscope $end
$scope module UUT_and2_gate $end
$var wire 1 % a $end
$var wire 1 & b $end
$var wire 1 ! y $end
$upscope $end
$upscope $end
$enddefinitions $end
$comment Show the parameter values. $end
$dumpall
b10100 $
$end
#0
$dumpvars
b10000000000000000000000000000011 -
b100 ,
0+
b1 *
0)
b0 (
b1001001010011100100100101010100 '
0&
0%
0#
0"
0!
$end
#100
1)
#200
0)
#250
b10 *
b101101 '
#300
1)
#400
0)
#450
b11 *
1&
#500
1)
#600
0)
#650
b100 *
0&
1%
#700
1)
#800
0)
#850
1#
1"
1!
b101 *
1+
1&
#900
1)
#1000
0)
#1050
b11111111111111111111111111111111 ,
