basic-code/sequential-logic/d_flip_flop/d_flip_flop.v
// A d flip-flop which is pulse-triggered can save input data on output.

module d_flip_flop_gate (
    input       clk,        // Clock
    input       d,          // Inputs
    output      q,          // Output
    output      qbar);      //

    // INTERNAL WIRES
    wire        s, r;
    wire        s1, r1;
  
    assign s = d;
  
    // NOT1
    not (r, s);

    // SR FLIP-FLOP ---------------------------------

    // NAND3
    nand (s1, s, clk);

    // NAND4
    nand (r1, r, clk);

    // SR-LATCH -------------------------------------
    
    // NAND1
    nand (q, s1, qbar);

    // NAND2
    nand (qbar, r1, q);

endmodule

module d_flip_flop_dataflow (
    input       clk,        // Clock
    input       d,          // Inputs
    output      q,          // Output
    output      qbar);      //

    assign s = d;
    assign r = ~d;

    // SR FLIP-FLOP ---------------------------------

    // INTERNAL WIRES
    wire        s1, r1;
  
    // NAND3
    assign s1 = ~(s & clk);

    // NAND4
    assign r1 = ~(r & clk);

    // SR- LATCH -------------------------------------
    
    // NAND1
    assign q = ~(s1 & qbar);

    // NAND2
    assign qbar = ~(r1 & q);

endmodule

module d_flip_flop_behavioral (
    input       clk,        // Clock
    input       d,          // Inputs
    output reg  q,          // Output
    output      qbar);      //

    parameter    DATA0 = 1'b0,
                 DATA1 = 1'b1;

    // INTERNAL WIRES
    assign qbar = ~q;

    always @(posedge clk) begin
        case({d})
            DATA0 : q <= 1'b0;
            DATA1 : q <= 1'b1;
        endcase
    end

endmodule

basic-code/sequential-logic/d_flip_flop/d_flip_flop_tb.v
`timescale 1ns / 100ps // time-unit = 1 ns, precision = 100 ps

// include files are in d_flip_flop.vh

module D_FLIP_FLOP_TB ();

    // INPUT PROBES
    reg             D;

    // OUTPUT PROBES
    wire            Q_gate, QBAR_gate;
    wire            Q_data, QBAR_data;
    wire            Q_beh, QBAR_beh;

    // FOR TESTING  
    reg             CLK;
    reg [31:0]      VECTORCOUNT, ERRORS;
    reg             QEXPECTED;
    integer         FD, COUNT;
    reg [8*32-1:0]  COMMENT;

    // UNIT UNDER TEST (gate)
    d_flip_flop_gate UUT_d_flip_flop_gate(
        .clk(CLK),
        .d(D),
        .q(Q_gate), .qbar(QBAR_gate)
    );

    // UNIT UNDER TEST (dataflow)
    d_flip_flop_dataflow UUT_d_flip_flop_dataflow(
        .clk(CLK),
        .d(D),
        .q(Q_data), .qbar(QBAR_data)
    );

        // UNIT UNDER TEST (behavioral)
    d_flip_flop_behavioral UUT_d_flip_flop_behavioral(
        .clk(CLK),
        .d(D),
        .q(Q_beh), .qbar(QBAR_beh)
    );

    // SAVE EVERYTHING FROM TOP TB MODULE IN A DUMP FILE
    initial begin
        $dumpfile("d_flip_flop_tb.vcd");
        $dumpvars(0, D_FLIP_FLOP_TB);
    end

    // CLK PERIOD
    localparam CLKPERIOD = 20;

    // CLK
    always begin
        #(CLKPERIOD/2) CLK = ~CLK;
    end

    // INITIALIZE TESTBENCH
    initial begin

        // OPEN VECTOR FILE - THROW AWAY FIRST LINE
        FD=$fopen("d_flip_flop_tb.tv","r");
        COUNT = $fscanf(FD, "%s", COMMENT);
        // $display ("FIRST LINE IS: %s", COMMENT);

        // INIT TESTBENCH
        COUNT = $fscanf(FD, "%s %b %b", COMMENT, D, QEXPECTED);
        CLK = 0;
        VECTORCOUNT = 0;
        ERRORS = 0;
        COMMENT ="";

        // DISPAY OUTPUT AND MONITOR
        $display();
        $display("TEST START --------------------------------");
        $display();
        $display("                                 GATE  DATA   BEH");
        $display("                 | TIME(ns) | S |  Q  |  Q  |  Q  |");
        $display("                 ----------------------------------");
        $monitor("%4d  %10s | %8d | %1d |  %1d  |  %1d  |  %1d  |", VECTORCOUNT, COMMENT, $time, D, Q_gate, Q_data, Q_beh);

    end

    // APPLY TEST VECTORS ON NEG EDGE CLK (ADD DELAY)
    always @(negedge CLK) begin

        // WAIT A BIT (AFTER CHECK)
        #5;

        // GET VECTORS FROM TB FILE
        COUNT = $fscanf(FD, "%s %b %b", COMMENT, D, QEXPECTED);

        // CHECK IF EOF - PRINT SUMMARY, CLOSE VECTOR FILE AND FINISH TB
        if (COUNT == -1) begin
            $fclose(FD);
            $display();
            $display(" VECTORS: %4d", VECTORCOUNT);
            $display("  ERRORS: %4d", ERRORS);
            $display();
            $display("TEST END ----------------------------------");
            $display();
            $finish;
        end

        // GET ANOTHER VECTOR
        VECTORCOUNT = VECTORCOUNT + 1;

    end

    // CHECK TEST VECTORS ON POS EGDE CLK
    always @(posedge CLK) begin

        // WAIT A BIT
        #5;

        // CHECK EACH VECTOR RESULT
        if (Q_gate !== QEXPECTED) begin
            $display("***ERROR (gate) - Expected Q = %b", QEXPECTED);
            ERRORS = ERRORS + 1;
        end
        if (Q_data !== QEXPECTED) begin
            $display("***ERROR (dataflow) - Expected Q = %b", QEXPECTED);
            ERRORS = ERRORS + 1;
        end
        if (Q_beh !== QEXPECTED) begin
            $display("***ERROR (behavioral) - Expected Q = %b", QEXPECTED);
            ERRORS = ERRORS + 1;
        end

    end   

endmodule

basic-code/sequential-logic/d_flip_flop/d_flip_flop_tb.vcd
$date
	Sat May 20 17:16:53 2023
$end
$version
	Icarus Verilog
$end
$timescale
	100ps
$end
$scope module D_FLIP_FLOP_TB $end
$var wire 1 ! Q_gate $end
$var wire 1 " Q_data $end
$var wire 1 # Q_beh $end
$var wire 1 $ QBAR_gate $end
$var wire 1 % QBAR_data $end
$var wire 1 & QBAR_beh $end
$var parameter 32 ' CLKPERIOD $end
$var reg 1 ( CLK $end
$var reg 256 ) COMMENT [255:0] $end
$var reg 1 * D $end
$var reg 32 + ERRORS [31:0] $end
$var reg 1 , QEXPECTED $end
$var reg 32 - VECTORCOUNT [31:0] $end
$var integer 32 . COUNT [31:0] $end
$var integer 32 / FD [31:0] $end
$scope module UUT_d_flip_flop_behavioral $end
$var wire 1 ( clk $end
$var wire 1 * d $end
$var wire 1 & qbar $end
$var parameter 1 0 DATA0 $end
$var parameter 1 1 DATA1 $end
$var reg 1 # q $end
$upscope $end
$scope module UUT_d_flip_flop_dataflow $end
$var wire 1 ( clk $end
$var wire 1 * d $end
$var wire 1 " q $end
$var wire 1 % qbar $end
$var wire 1 2 r $end
$var wire 1 3 r1 $end
$var wire 1 4 s $end
$var wire 1 5 s1 $end
$upscope $end
$scope module UUT_d_flip_flop_gate $end
$var wire 1 ( clk $end
$var wire 1 * d $end
$var wire 1 ! q $end
$var wire 1 $ qbar $end
$var wire 1 6 r $end
$var wire 1 7 r1 $end
$var wire 1 8 s $end
$var wire 1 9 s1 $end
$upscope $end
$upscope $end
$enddefinitions $end
$comment Show the parameter values. $end
$dumpall
11
00
b10100 '
$end
#0
$dumpvars
19
08
17
16
15
04
13
12
b10000000000000000000000000000011 /
b11 .
b1 -
0,
b0 +
0*
b1001001010011100100100101010100 )
0(
x&
x%
x$
x#
x"
x!
$end
#100
1&
0#
0"
1%
0!
03
1$
07
1(
#200
13
17
0(
#250
b10 -
b10001000100000101010100010000010101111100110000 )
#300
03
07
1(
#400
13
17
0(
#450
02
06
b11 -
1,
14
18
1*
b10001000100000101010100010000010101111100110001 )
#500
0&
1#
0%
1"
0$
05
1!
09
1(
#600
15
19
0(
#650
12
16
b100 -
0,
04
08
0*
b10001000100000101010100010000010101111100110000 )
#700
1&
0#
0"
1%
0!
03
1$
07
1(
#800
13
17
0(
#850
02
06
b101 -
1,
14
18
1*
b10001000100000101010100010000010101111100110001 )
#900
0&
1#
0%
1"
0$
05
1!
09
1(
#1000
15
19
0(
#1050
b11111111111111111111111111111111 .
