sequential-logic/shifters/left_shift_register/left_shift_register.v
// A 4-bit left shift register.

module left_shift_register_behavioral (
    input            clk,           // clk
    input            rst,           // Reset
    input            d,             // d
    output reg [3:0] out);          // out

    // LEFT SHIFT REGISTER
    // ALWAYS BLOCK with NON-BLOCKING PROCEDURAL ASSIGNMENT STATEMENT
    always @ (posedge clk) begin
        if (rst) begin
            out <= 4'b0000;
        end else begin
            out <= {out[2:0], d};
        end
    end

endmodule

sequential-logic/shifters/left_shift_register/left_shift_register_tb.v
`timescale 1ns / 100ps // time-unit = 1 ns, precision = 100 ps

// include files in left_shift_register.vh

module LEFT_SHIFT_REGISTER_TB;

    // DATA TYPES - DECLARE REGISTERS AND WIRES (PROBES)
    reg             CLK;
    reg             RST;
    reg             D;
    wire [3:0]      OUT;

    // FOR TESTING  
    reg [31:0]      VECTORCOUNT, ERRORS;
    reg [3:0]       OUTEXP;
    integer         FD, COUNT;
    reg [8*32-1:0]  COMMENT;

    // UNIT UNDER TEST (behavioral)
    left_shift_register_behavioral UUT_left_shift_register_behavioral(
        .clk(CLK),
        .rst(RST),
        .d(D),
        .out(OUT)
    );

    // SAVE EVERYTHING FROM TOP TB MODULE IN A DUMP FILE
    initial begin
        $dumpfile("left_shift_register_tb.vcd");
        $dumpvars(0, LEFT_SHIFT_REGISTER_TB);
    end

    // CLK PERIOD
    localparam CLKPERIOD = 20;

    // CLK
    always begin
        #(CLKPERIOD/2) CLK = ~CLK;
    end

    // INITIALIZE TESTBENCH
    initial begin

        // OPEN VECTOR FILE - THROW AWAY FIRST LINE
        FD=$fopen("left_shift_register_tb.tv","r");
        COUNT = $fscanf(FD, "%s", COMMENT);
        // $display ("FIRST LINE IS: %s", COMMENT);

        // INIT TESTBENCH
        COUNT = $fscanf(FD, "%s %b %b %b", COMMENT, RST, D, OUTEXP);
        CLK = 0;
        VECTORCOUNT = 1;
        ERRORS = 0;

        // DISPAY OUTPUT AND MONITOR
        $display();
        $display("TEST START --------------------------------");
        $display();
        $display("                 | TIME(ns) | RST | D | OUT  |");
        $display("                 -----------------------------");
        // $monitor("%4d  %10s | %8d | %b   | %1b | %1b |", VECTORCOUNT, COMMENT, $time, RST, D, OUT);

    end

    // APPLY TEST VECTORS ON NEG EDGE CLK (ADD DELAY)
    always @(negedge CLK) begin

        // WAIT A BIT (AFTER CHECK)
        #5;

        // GET VECTORS FROM TB FILE
        COUNT = $fscanf(FD, "%s %b %b %b", COMMENT, RST, D, OUTEXP);

        // CHECK IF EOF - PRINT SUMMARY, CLOSE VECTOR FILE AND FINISH TB
        if (COUNT == -1) begin
            $fclose(FD);
            $display();
            $display(" VECTORS: %4d", VECTORCOUNT);
            $display("  ERRORS: %4d", ERRORS);
            $display();
            $display("TEST END ----------------------------------");
            $display();
            $finish;
        end

        // GET ANOTHER VECTOR
        VECTORCOUNT = VECTORCOUNT + 1;

    end

    // CHECK TEST VECTORS ON POS EGDE CLK
    always @(posedge CLK) begin

        // WAIT A BIT
        #5;

        // DISPLAY OUTPUT ON POS EDGE CLK
        $display("%4d  %10s | %8d | %b   | %1b | %1b |", VECTORCOUNT, COMMENT, $time, RST, D, OUT);

        // CHECK EACH VECTOR RESULT
        if (OUT !== OUTEXP) begin
            $display("***ERROR (behavioral) - Expected OUT = %b", OUTEXP);
            ERRORS = ERRORS + 1;
        end

    end   

endmodule

sequential-logic/shifters/left_shift_register/left_shift_register_tb.vcd
$date
	Sat May 20 19:46:11 2023
$end
$version
	Icarus Verilog
$end
$timescale
	100ps
$end
$scope module LEFT_SHIFT_REGISTER_TB $end
$var wire 4 ! OUT [3:0] $end
$var parameter 32 " CLKPERIOD $end
$var reg 1 # CLK $end
$var reg 256 $ COMMENT [255:0] $end
$var reg 1 % D $end
$var reg 32 & ERRORS [31:0] $end
$var reg 4 ' OUTEXP [3:0] $end
$var reg 1 ( RST $end
$var reg 32 ) VECTORCOUNT [31:0] $end
$var integer 32 * COUNT [31:0] $end
$var integer 32 + FD [31:0] $end
$scope module UUT_left_shift_register_behavioral $end
$var wire 1 # clk $end
$var wire 1 % d $end
$var wire 1 ( rst $end
$var reg 4 , out [3:0] $end
$upscope $end
$upscope $end
$enddefinitions $end
$comment Show the parameter values. $end
$dumpall
b10100 "
$end
#0
$dumpvars
bx ,
b10000000000000000000000000000011 +
b100 *
b1 )
0(
bx0 '
b0 &
0%
b1001001010011100100100101010100 $
0#
bx !
$end
#100
bx0 !
bx0 ,
1#
#200
0#
#250
b10 )
b0 '
1(
b101001001000101010100110100010101010100 $
#300
b0 !
b0 ,
1#
#400
0#
#450
b11 )
b1 '
1%
0(
b1000100010000010101010001000001 $
#500
b1 !
b1 ,
1#
#600
0#
#650
b100 )
b10 '
0%
b101001101001000010010010100011001010100 $
#700
b10 !
b10 ,
1#
#800
0#
#850
b101 )
b101 '
1%
b1000100010000010101010001000001 $
#900
b101 !
b101 ,
1#
#1000
0#
#1050
b110 )
b1010 '
0%
b101001101001000010010010100011001010100 $
#1100
b1010 !
b1010 ,
1#
#1200
0#
#1250
b111 )
b100 '
#1300
b100 !
b100 ,
1#
#1400
0#
#1450
b1000 )
b1000 '
#1500
b1000 !
b1000 ,
1#
#1600
0#
#1650
b1001 )
b0 '
#1700
b0 !
b0 ,
1#
#1800
0#
#1850
b11111111111111111111111111111111 *
