sequential-logic/shifters/left_shift_register/left_shift_register.v
// A 4-bit left shift register.

module left_shift_register(
    input        clk,           // clk
    input        rst,           // Reset
    input        d,             // d
    output [3:0] out            // out
);

reg [3:0] out;

always @ (posedge clk) begin
    if (rst) begin
        out <= 4'b0000;      
    end else begin
        out <= {out[2:0], d};
    end
end

endmodule

sequential-logic/shifters/left_shift_register/left_shift_register_tb.vh
`timescale 1ns / 1ns

// include files in left-shift-register-headerfiles.vh

module left_shift_register_tb;

// DATA TYPES - DECLAIR INPUTS AND OUTPUTS
reg        CLK, RST;
reg        D;
wire [3:0] OUT;
integer    i;
integer    seed=1;

// UUT
left_shift_register uut(
    .clk(CLK), .rst(RST),
    .d(D),
    .out(OUT)
);

// FILES
initial begin
    $dumpfile("left-shift-register-tb.vcd");
    $dumpvars(0, left_shift_register_tb);
end

// CLOCK
always begin
    #10 CLK = ~CLK;
end

// TESTCASE
initial begin
    $display("test start");
    CLK = 0;
    RST = 0;
    D = 0;

    // RESET
    #15
    RST = 1;
    #20
    RST = 0;
    #20

    // PUMP IN RANDOM NUMBERS
    for (i = 0; i < 30; i = i + 1) begin
        @ (posedge CLK) begin
            D <= $random(seed);
        end
    end
    
    // DONE
    #20

    $display("test complete");
    $finish;
end

endmodule

sequential-logic/shifters/left_shift_register/left-shift-register-tb.vcd
$date
	Wed Nov 11 21:15:14 2020
$end
$version
	Icarus Verilog
$end
$timescale
	1ns
$end
$scope module left_shift_register_tb $end
$var wire 4 ! OUT [3:0] $end
$var reg 1 " CLK $end
$var reg 1 # D $end
$var reg 1 $ RST $end
$var integer 32 % i [31:0] $end
$var integer 32 & seed [31:0] $end
$scope module uut $end
$var wire 1 " clk $end
$var wire 1 # d $end
$var wire 1 $ rst $end
$var reg 4 ' out [3:0] $end
$upscope $end
$upscope $end
$enddefinitions $end
#0
$dumpvars
bx '
b1 &
bx %
0$
0#
0"
bx !
$end
#10
bx0 !
bx0 '
1"
#15
1$
#20
0"
#30
b0 !
b0 '
1"
#35
0$
#40
0"
#50
1"
#55
b0 %
#60
0"
#70
b1 %
b10000110111001110 &
1"
#80
0"
#90
b10 %
b11100010110011000001111110111 &
1"
#100
0"
#110
b11 %
b11000011010110010011011111001100 &
1"
#120
0"
#130
b100 %
b101110000100110000101001011101 &
1"
#140
0"
#150
b101 %
b11100111001000110000010101111010 &
1"
#160
0"
#170
1#
b110 %
b11100011110011001001010010110011 &
1"
#180
0"
#190
b1 !
b1 '
0#
b111 %
b1100011000100110010101001011000 &
1"
#200
0"
#210
1#
b10 !
b10 '
b1000 %
b1111001110101110110000001111001 &
1"
#220
0"
#230
b101 !
b101 '
b1001 %
b11100001110101110110010111100110 &
1"
#240
0"
#250
b1011 !
b1011 '
b1010 %
b101111100011110100011100101111 &
1"
#260
0"
#270
b111 !
b111 '
b1011 %
b10100011100010000110001110100100 &
1"
#280
0"
#290
b1111 !
b1111 '
b1100 %
b1000100111010110001111001010101 &
1"
#300
0"
#310
0#
b1101 %
b111111001001101001101100010010 &
1"
#320
0"
#330
1#
b1110 !
b1110 '
b1110 %
b100010110111000001011101101011 &
1"
#340
0"
#350
b1101 !
b1101 '
b1111 %
b101110110110100010111110110000 &
1"
#360
0"
#370
b1011 !
b1011 '
b10000 %
b11001000110101000001111111110001 &
1"
#380
0"
#390
b111 !
b111 '
0#
b10001 %
b10110111011011011101000011111110 &
1"
#400
0"
#410
1#
b1110 !
b1110 '
b10010 %
b1000111100010110100000101100111 &
1"
#420
0"
#430
b1101 !
b1101 '
0#
b10011 %
b10011110001111001001101001111100 &
1"
#440
0"
#450
1#
b1010 !
b1010 '
b10100 %
b1100100110111000000000101001101 &
1"
#460
0"
#470
b101 !
b101 '
b10101 %
b11110001100010101111001110101010 &
1"
#480
0"
#490
0#
b1011 !
b1011 '
b10110 %
b1101110010011101100000100100011 &
1"
#500
0"
#510
b110 !
b110 '
b10111 %
b10110000000100111000000001000 &
1"
#520
0"
#530
1#
b1100 !
b1100 '
b11000 %
b101111101011000001111001101001 &
1"
#540
0"
#550
b1001 !
b1001 '
b11001 %
b1000110010001010111100010110 &
1"
#560
0"
#570
b11 !
b11 '
b11010 %
b11101000101011100101001010011111 &
1"
#580
0"
#590
b111 !
b111 '
0#
b11011 %
b10000000011010010011110001010100 &
1"
#600
0"
#610
1#
b1110 !
b1110 '
b11100 %
b1101000101010011001001101000101 &
1"
#620
0"
#630
b1101 !
b1101 '
b11101 %
b11111111100010100110111101000010 &
1"
#640
0"
#650
b1011 !
b1011 '
b11110 %
b11000110000110111000111011011 &
1"
#660
0"
#670
b111 !
b111 '
1"
