sequential-logic/finite-state-machines/mealy_state_machine/mealy_state_machine.v
// Recognize the pattern 00110 in a serial stream.

module mealy_state_machine_behavioral (
    input        clk,           // clk
    input        rst,           // Reset
    input        in,            // Serial in
    output reg   found);        // Found pattern

    // DATA TYPES
    reg [2:0] state;

    // STATES - BINARY ENCODED STYLE - USE ANY STYLE YOU WANT
    parameter [2:0] START     = 3'b000;
    parameter [2:0] ZERO      = 3'b001;
    parameter [2:0] WAIT      = 3'b010;
    parameter [2:0] S1        = 3'b011;
    parameter [2:0] S2        = 3'b100;
    parameter [2:0] S3        = 3'b101;

    // MEALY STATE MACHINE
    // ALWAYS BLOCK with NON-BLOCKING PROCEDURAL ASSIGNMENT STATEMENT
    always @ (posedge clk) begin
        if (rst) begin
            state <= START;
            found <= 1'b0;
        end else begin
            case (state)
                START: begin
                    if (in==0)  begin state <= ZERO;  found <= 1'b0; end
                    else        begin state <= START; found <= 1'b0; end
                end
                ZERO: begin
                    if (in==0)  begin state <= WAIT;  found <= 1'b0; end
                    else        begin state <= START; found <= 1'b0; end
                end
                WAIT: begin
                    if (in==1)  begin state <= S1;    found <= 1'b0; end
                    else        begin state <= WAIT;  found <= 1'b0; end
                end
                S1: begin
                    if (in==1)  begin state <= S2;    found <= 1'b0; end
                    else        begin state <= ZERO;  found <= 1'b0; end
                end
                S2:begin
                    if (in==0)  begin state <= S3;    found <= 1'b0; end
                    else        begin state <= START; found <= 1'b0; end
                end
                S3:begin
                    if (in==1)  begin state <= START; found <= 1'b1; end // Found pattern
                    else        begin state <= WAIT;  found <= 1'b0; end
                end
            endcase
        end
    end

endmodule

sequential-logic/finite-state-machines/mealy_state_machine/mealy_state_machine_tb.v
`timescale 1ns / 100ps // time-unit = 1 ns, precision = 100 ps

// include files in mealy_state_machine.vh

module MEALY_STATE_MACHINE_TB;

    // DATA TYPES - DECLARE REGISTERS AND WIRES (PROBES)
    reg        RST;
    reg        CLK;
    reg        IN;
    wire       FOUND;

    // FOR TESTING  
    reg [31:0]      VECTORCOUNT, ERRORS;
    reg             FOUNDEXP;
    integer         FD, COUNT;
    reg [8*32-1:0]  COMMENT;

    // UNIT UNDER TEST
    mealy_state_machine_behavioral UUT_mealy_state_machine_behavioral(
        .rst(RST),
        .clk(CLK),
        .in(IN),
        .found(FOUND)
    );

    // SAVE EVERYTHING FROM TOP TB MODULE IN A DUMP FILE
    initial begin
        $dumpfile("mealy_state_machine_tb.vcd");
        $dumpvars(0, MEALY_STATE_MACHINE_TB);
    end

    // CLK PERIOD
    localparam CLKPERIOD = 20;

    // CLK
    always begin
        #(CLKPERIOD/2) CLK = ~CLK;
    end

    // INITIALIZE TESTBENCH
    initial begin

        // OPEN VECTOR FILE - THROW AWAY FIRST LINE
        FD=$fopen("mealy_state_machine_tb.tv","r");
        COUNT = $fscanf(FD, "%s", COMMENT);
        // $display ("FIRST LINE IS: %s", COMMENT);

        // INIT TESTBENCH
        COUNT = $fscanf(FD, "%s %b %b %b", COMMENT, RST, IN, FOUNDEXP);
        CLK = 0;
        VECTORCOUNT = 0;
        ERRORS = 0;
        COMMENT ="";

        // DISPAY OUTPUT AND MONITOR
        $display();
        $display("TEST START --------------------------------");
        $display();
        $display("                 | TIME(ns) | RST | IN | FOUND |");
        $display("                 -------------------------------");
        $monitor("%4d  %10s | %8d |  %1d  | %1d  |   %1d   |", VECTORCOUNT, COMMENT, $time, RST, IN, FOUND);

    end

    // APPLY TEST VECTORS ON NEG EDGE CLK (ADD DELAY)
    always @(negedge CLK) begin

        // WAIT A BIT (AFTER CHECK)
        #5;

        // GET VECTORS FROM TB FILE
        COUNT = $fscanf(FD, "%s %b %b %b", COMMENT, RST, IN, FOUNDEXP);

        // CHECK IF EOF - PRINT SUMMARY, CLOSE VECTOR FILE AND FINISH TB
        if (COUNT == -1) begin
            $fclose(FD);
            $display();
            $display(" VECTORS: %4d", VECTORCOUNT);
            $display("  ERRORS: %4d", ERRORS);
            $display();
            $display("TEST END ----------------------------------");
            $display();
            $finish;
        end

        // GET ANOTHER VECTOR
        VECTORCOUNT = VECTORCOUNT + 1;

    end

    // CHECK TEST VECTORS ON POS EGDE CLK
    always @(posedge CLK) begin

        // WAIT A BIT
        #5;

        // CHECK EACH VECTOR RESULT
        if (FOUNDEXP !== FOUND) begin
            $display("***ERROR (behavioral) - Expected FOUND=%b", FOUNDEXP);
            ERRORS = ERRORS + 1;
        end

    end   

endmodule

sequential-logic/finite-state-machines/mealy_state_machine/mealy_state_machine_tb.vcd
$date
	Tue May  9 02:56:08 2023
$end
$version
	Icarus Verilog
$end
$timescale
	100ps
$end
$scope module MEALY_STATE_MACHINE_TB $end
$var wire 1 ! FOUND $end
$var parameter 32 " CLKPERIOD $end
$var reg 1 # CLK $end
$var reg 256 $ COMMENT [255:0] $end
$var reg 32 % ERRORS [31:0] $end
$var reg 1 & FOUNDEXP $end
$var reg 1 ' IN $end
$var reg 1 ( RST $end
$var reg 32 ) VECTORCOUNT [31:0] $end
$var integer 32 * COUNT [31:0] $end
$var integer 32 + FD [31:0] $end
$scope module UUT_mealy_state_machine_behavioral $end
$var wire 1 # clk $end
$var wire 1 ' in $end
$var wire 1 ( rst $end
$var parameter 3 , S1 $end
$var parameter 3 - S2 $end
$var parameter 3 . S3 $end
$var parameter 3 / START $end
$var parameter 3 0 WAIT $end
$var parameter 3 1 ZERO $end
$var reg 1 ! found $end
$var reg 3 2 state [2:0] $end
$upscope $end
$upscope $end
$enddefinitions $end
$comment Show the parameter values. $end
$dumpall
b1 1
b10 0
b0 /
b101 .
b100 -
b11 ,
b10100 "
$end
#0
$dumpvars
bx 2
b10000000000000000000000000000011 +
b100 *
b0 )
0(
x'
x&
b0 %
b0 $
0#
x!
$end
#100
1#
#200
0#
#250
b1 )
0&
0'
1(
b101001001000101010100110100010101010100 $
#300
0!
b0 2
1#
#400
0#
#450
b10 )
1'
0(
b101001101010100010000010101001001010100 $
#500
1#
#600
0#
#650
b11 )
#700
1#
#800
0#
#850
b100 )
0'
b1011010010001010101001001001111 $
#900
b1 2
1#
#1000
0#
#1050
b101 )
b1010111010000010100100101010100 $
#1100
b10 2
1#
#1200
0#
#1250
b110 )
#1300
1#
#1400
0#
#1450
b111 )
#1500
1#
#1600
0#
#1650
b1000 )
#1700
1#
#1800
0#
#1850
b1001 )
1'
b101001100110001 $
#1900
b11 2
1#
#2000
0#
#2050
b1010 )
b101001100110010 $
#2100
b100 2
1#
#2200
0#
#2250
b1011 )
0'
b101001100110011 $
#2300
b101 2
1#
#2400
0#
#2450
b1100 )
1&
1'
b101001101010100010000010101001001010100 $
#2500
1!
b0 2
1#
#2600
0#
#2650
b1101 )
0&
#2700
0!
1#
#2800
0#
#2850
b1110 )
0'
b1011010010001010101001001001111 $
#2900
b1 2
1#
#3000
0#
#3050
b1111 )
b1010111010000010100100101010100 $
#3100
b10 2
1#
#3200
0#
#3250
b10000 )
#3300
1#
#3400
0#
#3450
b10001 )
#3500
1#
#3600
0#
#3650
b10010 )
#3700
1#
#3800
0#
#3850
b10011 )
1'
b101001100110001 $
#3900
b11 2
1#
#4000
0#
#4050
b10100 )
0'
b1011010010001010101001001001111 $
#4100
b1 2
1#
#4200
0#
#4250
b10101 )
b1010111010000010100100101010100 $
#4300
b10 2
1#
#4400
0#
#4450
b10110 )
1'
b101001100110001 $
#4500
b11 2
1#
#4600
0#
#4650
b10111 )
b101001100110010 $
#4700
b100 2
1#
#4800
0#
#4850
b11000 )
0'
b101001100110011 $
#4900
b101 2
1#
#5000
0#
#5050
b11001 )
b1010111010000010100100101010100 $
#5100
b10 2
1#
#5200
0#
#5250
b11010 )
#5300
1#
#5400
0#
#5450
b11011 )
1'
b101001100110001 $
#5500
b11 2
1#
#5600
0#
#5650
b11100 )
b101001100110010 $
#5700
b100 2
1#
#5800
0#
#5850
b11101 )
0'
b101001100110011 $
#5900
b101 2
1#
#6000
0#
#6050
b11110 )
1&
1'
b101001101010100010000010101001001010100 $
#6100
1!
b0 2
1#
#6200
0#
#6250
b11111111111111111111111111111111 *
