sequential-logic/arbiters/priority-arbiter/priority-arbiter.v
//  A three level Priority Arbiter with asynchronous reset
module priority_arbitor(
    input clk,          // Clock  
    input rst,          // Reset
    input req_0,        // Request 0
    input req_1,        // Request 1
    input req_2,        // Request 2
    output gnt_0,       // Grant 0
    output gnt_1,       // Grant 1
    output gnt_2        // Grant 2
);

// DATA TYPES
wire req_0, req_1, req_2;
wire clk, rst;
reg gnt_0, gnt_1, gnt_2;

always @ (posedge clk or posedge rst)
begin
    if (rst) begin
        gnt_0 <= 0;
        gnt_1 <= 0;
        gnt_2 <= 0;
    end else if (req_0) begin
        gnt_0 <= 1;
        gnt_1 <= 0;
        gnt_2 <= 0;
    end else if (req_1) begin
        gnt_0 <= 0;
        gnt_1 <= 1;
        gnt_2 <= 0;
    end else if (req_2) begin
        gnt_0 <= 0;
        gnt_1 <= 0;
        gnt_2 <= 1;
    end else begin
        gnt_0 <= 0;
        gnt_1 <= 0;
        gnt_2 <= 0;
    end
end

endmodule

sequential-logic/arbiters/priority-arbiter/priority-arbiter-tb.v
`timescale 1ns / 1ns
`include "priority-arbiter.v"

module priority_arbiter_tb;

// DATA TYPES - DECLAIR INPUTS AND OUTPUTS
reg  CLK, RST;
reg  REQ_0, REQ_1, REQ_2;
wire GNT_0, GNT_1, GNT_2;

// UUT
priority_arbitor uut(
    .clk(CLK), .rst(RST),
    .req_0(REQ_0), .req_1(REQ_1), .req_2(REQ_2),
    .gnt_0(GNT_0), .gnt_1(GNT_1), .gnt_2(GNT_2)
);

// FILES
initial begin
    $dumpfile("priority-arbiter-tb.vcd");
    $dumpvars(0, priority_arbiter_tb);
end

// CLOCK
always begin
    #10 CLK = ~CLK;
end

// SIMULATION
initial begin
    $display("test start");
    CLK = 0;
    RST = 0;
    {REQ_2, REQ_1, REQ_0} = 3'b000;
    
    #15; {REQ_2, REQ_1, REQ_0} = 3'b001;
    #20; {REQ_2, REQ_1, REQ_0} = 3'b010;
    #20; {REQ_2, REQ_1, REQ_0} = 3'b011;
    #20; {REQ_2, REQ_1, REQ_0} = 3'b100;
    #20; {REQ_2, REQ_1, REQ_0} = 3'b101;
    #20; {REQ_2, REQ_1, REQ_0} = 3'b110;
    #20; {REQ_2, REQ_1, REQ_0} = 3'b111;
    #20  RST = 1;
    #20

    $display("test complete");
    $finish;
end

endmodule

sequential-logic/arbiters/priority-arbiter/priority-arbiter-tb.vcd
$date
	Tue Oct 27 09:53:48 2020
$end
$version
	Icarus Verilog
$end
$timescale
	1ns
$end
$scope module priority_arbiter_tb $end
$var wire 1 ! GNT_2 $end
$var wire 1 " GNT_1 $end
$var wire 1 # GNT_0 $end
$var reg 1 $ CLK $end
$var reg 1 % REQ_0 $end
$var reg 1 & REQ_1 $end
$var reg 1 ' REQ_2 $end
$var reg 1 ( RST $end
$scope module uut $end
$var wire 1 $ clk $end
$var wire 1 % req_0 $end
$var wire 1 & req_1 $end
$var wire 1 ' req_2 $end
$var wire 1 ( rst $end
$var reg 1 # gnt_0 $end
$var reg 1 " gnt_1 $end
$var reg 1 ! gnt_2 $end
$upscope $end
$upscope $end
$enddefinitions $end
#0
$dumpvars
0(
0'
0&
0%
0$
x#
x"
x!
$end
#10
0!
0"
0#
1$
#15
1%
#20
0$
#30
1#
1$
#35
1&
0%
#40
0$
#50
1"
0#
1$
#55
1%
#60
0$
#70
0"
1#
1$
#75
1'
0&
0%
#80
0$
#90
1!
0#
1$
#95
1%
#100
0$
#110
0!
1#
1$
#115
1&
0%
#120
0$
#130
1"
0#
1$
#135
1%
#140
0$
#150
0"
1#
1$
#155
0#
1(
