basic-code/combinational-logic/nand4/nand4.v
// 4-input NAND gate used in my programable-8-bit-microprocessor

module nand4(
    input       a, b, c, d,    // 4-Input
    output      y              // Output
);

    // CONTINUOUS ASSIGNMENT STATEMENT
    assign y = ~(a & b & c & d);

endmodule

basic-code/combinational-logic/nand4/nand4_tb.v
`timescale 1ns / 100ps // time-unit = 1 ns, precision = 100 ps

// include files are in nand4.vh

module NAND4_TB;

    // DATA TYPES - DECLARE REGISTERS AND WIRES (PROBES)
    reg        A, B, C, D;
    wire       Y;
    integer    i;

    // UNIT UNDER TEST
    nand4 UUT_nand4(
        .a(A), .b(B), .c(C), .d(D),
        .y(Y)
    );

    // SAVE EVERYTHING FROM TOP MODULE IN A DUMP FILE
    initial begin
        $dumpfile("nand4_tb.vcd");
        $dumpvars(0, NAND4_TB);
    end

    // TESTCASE - CHANGE REG VALUES
    initial begin
        $display("TEST START");
        $write("| TIME(ns) | A | B | C | D | Y |"); // header
        $display;

        // INCREMENT IN BINARY
        for (i=0; i<16; i=i+1) begin
            {A, B, C, D} = i;
            #20;
        end

        $display("TEST END");
        $finish;
    end

    // OUTPUT ON SCREEN FOR ANY CHANGE
    always @(*)
    begin
        $strobe("| %8d | %1d | %1d | %1d | %1d | %1d |", $time, A, B, C, D, Y);
    end

endmodule

basic-code/combinational-logic/nand4/nand4_tb.vcd
$date
	Mon Apr 10 20:32:07 2023
$end
$version
	Icarus Verilog
$end
$timescale
	100ps
$end
$scope module NAND4_TB $end
$var wire 1 ! Y $end
$var reg 1 " A $end
$var reg 1 # B $end
$var reg 1 $ C $end
$var reg 1 % D $end
$var integer 32 & i [31:0] $end
$scope module UUT_nand4 $end
$var wire 1 " a $end
$var wire 1 # b $end
$var wire 1 $ c $end
$var wire 1 % d $end
$var wire 1 ! y $end
$upscope $end
$upscope $end
$enddefinitions $end
$comment Show the parameter values. $end
$dumpall
$end
#0
$dumpvars
b0 &
0%
0$
0#
0"
1!
$end
#200
1%
b1 &
#400
1$
0%
b10 &
#600
1%
b11 &
#800
1#
0$
0%
b100 &
#1000
1%
b101 &
#1200
1$
0%
b110 &
#1400
1%
b111 &
#1600
1"
0#
0$
0%
b1000 &
#1800
1%
b1001 &
#2000
1$
0%
b1010 &
#2200
1%
b1011 &
#2400
1#
0$
0%
b1100 &
#2600
1%
b1101 &
#2800
1$
0%
b1110 &
#3000
0!
1%
b1111 &
#3200
b10000 &
