systems/pipelines/simple_pipeline/simple_pipeline.v
// A simple pipeline.

module simple_pipeline_behavioral (
    input                 clk,          // Clock
    input       [7:0]     a, b, c, d,   // Data
    output reg  [7:0]     f);           // Output Data

    reg [7:0] y1, y2, y3, d1, d2;

    // STAGE 1
    // ALWAYS BLOCK with NON-BLOCKING PROCEDURAL ASSIGNMENT STATEMENT
    always @ (posedge clk) begin
        y1 <= a + b;
        y2 <= c - d;
        d1 <= d;
    end

    // STAGE 2
    // ALWAYS BLOCK with NON-BLOCKING PROCEDURAL ASSIGNMENT STATEMENT
    always @ (posedge clk) begin
        y3 <= y1 + y2;
        d2 <=  d1;
    end

    // STAGE 3
    // ALWAYS BLOCK with NON-BLOCKING PROCEDURAL ASSIGNMENT STATEMENT
    always @ (posedge clk) begin
        f <= y3 * d2;
    end

endmodule

systems/pipelines/simple_pipeline/simple_pipeline_tb.v
`timescale 1ns / 100ps // time-unit = 1 ns, precision = 100 ps

// include files in simple_pipeline.vh

module SIMPLE_PIPELINE_TB;

    // DATA TYPES - DECLARE REGISTERS AND WIRES (PROBES)
    reg  [7:0]      A, B, C, D;
    reg             CLK;
    wire [7:0]      F;

    // FOR TESTING  
    reg [31:0]      VECTORCOUNT, ERRORS;
    reg [7:0]       FEXP;
    integer         FD, COUNT;
    reg [8*32-1:0]  COMMENT;

    // UNIT UNDER TEST (behavioral)
    simple_pipeline_behavioral UUT_simple_pipeline_behavioral(
        .clk(CLK),
        .a (A),
        .b (B),
        .c (C),
        .d (D),
        .f (F)
    );

    // SAVE EVERYTHING FROM TOP TB MODULE IN A DUMP FILE
    initial begin
        $dumpfile("simple_pipeline_tb.vcd");
        $dumpvars(0, SIMPLE_PIPELINE_TB);
    end

    // CLK PERIOD
    localparam CLKPERIOD = 20;

    // CLK
    always begin
        #(CLKPERIOD/2) CLK = ~CLK;
    end

    // INITIALIZE TESTBENCH
    initial begin

        // OPEN VECTOR FILE - THROW AWAY FIRST LINE
        FD=$fopen("simple_pipeline_tb.tv","r");
        COUNT = $fscanf(FD, "%s", COMMENT);
        // $display ("FIRST LINE IS: %s", COMMENT);

        // INIT TESTBENCH
        COUNT = $fscanf(FD, "%s %b %b %b %b %b", COMMENT, A, B, C, D, FEXP);
        CLK = 0;
        VECTORCOUNT = 0;
        ERRORS = 0;

        // DISPAY OUTPUT AND MONITOR
        $display();
        $display("TEST START --------------------------------");
        $display();
        $display("                               ");
        $display("                 | TIME(ns) |    A     |    B     |    C     |    D     |    F     |");
        $display("                 -------------------------------------------------------------------");
        $monitor("%4d  %10s | %8d | %1b | %1b | %1b | %1b | %1b |", VECTORCOUNT, COMMENT, $time, A, B, C, D, F);

    end

    // APPLY TEST VECTORS ON NEG EDGE CLK (ADD DELAY)
    always @(negedge CLK) begin

        // WAIT A BIT (AFTER CHECK)
        #5;

        // GET VECTORS FROM TB FILE
        COUNT = $fscanf(FD, "%s %b %b %b %b %b", COMMENT, A, B, C, D, FEXP);

        // CHECK IF EOF - PRINT SUMMARY, CLOSE VECTOR FILE AND FINISH TB
        if (COUNT == -1) begin
            $fclose(FD);
            $display();
            $display(" VECTORS: %4d", VECTORCOUNT);
            $display("  ERRORS: %4d", ERRORS);
            $display();
            $display("TEST END ----------------------------------");
            $display();
            $finish;
        end

        // GET ANOTHER VECTOR
        VECTORCOUNT = VECTORCOUNT + 1;

    end

    // CHECK TEST VECTORS ON POS EGDE CLK
    always @(posedge CLK) begin

        // WAIT A BIT
        #5;

        // CHECK EACH VECTOR RESULT
        if (F !== FEXP) begin
            $display("***ERROR (behavioral) - Expected F = %b", FEXP);
            ERRORS = ERRORS + 1;
        end

    end   

endmodule

systems/pipelines/simple_pipeline/simple_pipeline_tb.vcd
$date
	Thu May 11 04:54:37 2023
$end
$version
	Icarus Verilog
$end
$timescale
	100ps
$end
$scope module SIMPLE_PIPELINE_TB $end
$var wire 8 ! F [7:0] $end
$var parameter 32 " CLKPERIOD $end
$var reg 8 # A [7:0] $end
$var reg 8 $ B [7:0] $end
$var reg 8 % C [7:0] $end
$var reg 1 & CLK $end
$var reg 256 ' COMMENT [255:0] $end
$var reg 8 ( D [7:0] $end
$var reg 32 ) ERRORS [31:0] $end
$var reg 8 * FEXP [7:0] $end
$var reg 32 + VECTORCOUNT [31:0] $end
$var integer 32 , COUNT [31:0] $end
$var integer 32 - FD [31:0] $end
$scope module UUT_simple_pipeline_behavioral $end
$var wire 8 . a [7:0] $end
$var wire 8 / b [7:0] $end
$var wire 8 0 c [7:0] $end
$var wire 1 & clk $end
$var wire 8 1 d [7:0] $end
$var reg 8 2 d1 [7:0] $end
$var reg 8 3 d2 [7:0] $end
$var reg 8 4 f [7:0] $end
$var reg 8 5 y1 [7:0] $end
$var reg 8 6 y2 [7:0] $end
$var reg 8 7 y3 [7:0] $end
$upscope $end
$upscope $end
$enddefinitions $end
$comment Show the parameter values. $end
$dumpall
b10100 "
$end
#0
$dumpvars
bx 7
bx 6
bx 5
bx 4
bx 3
bx 2
b0 1
b0 0
b0 /
b0 .
b10000000000000000000000000000011 -
b110 ,
b0 +
bx *
b0 )
b0 (
b1001001010011100100100101010100 '
0&
b0 %
b0 $
b0 #
bx !
$end
#100
b0 2
b0 6
b0 5
1&
#200
0&
#250
b1 +
b100 (
b100 1
b101 %
b101 0
b10 $
b10 /
b1 #
b1 .
b100001101000001010011000100001100110001001011010011000100110110 '
#300
b0 3
b0 7
b100 2
b1 6
b11 5
1&
#400
0&
#450
b10 +
b0 *
b1 (
b1 1
b1100010 %
b1100010 0
b10110 $
b10110 /
b10110 #
b10110 .
b10000110100000101001100010000110011001000101101001100010011010000110001 '
#500
b1 2
b1100001 6
b101100 5
b100 3
b100 7
b0 !
b0 4
1&
#600
0&
#650
b11 +
b10000 *
b1000 (
b1000 1
b1001 %
b1001 0
b11 $
b11 /
b11 #
b11 .
b100001101000001010011000100001100110011001011010011010100110110 '
#700
b10000 !
b10000 4
b1 3
b10001101 7
b1000 2
b1 6
b110 5
1&
#800
0&
#850
b100 +
b10001101 *
b0 (
b0 1
b0 %
b0 0
b0 $
b0 /
b0 #
b0 .
b101101 '
#900
b0 2
b0 6
b0 5
b1000 3
b111 7
b10001101 !
b10001101 4
1&
#1000
0&
#1050
b101 +
b111000 *
#1100
b111000 !
b111000 4
b0 3
b0 7
1&
#1200
0&
#1250
b110 +
b0 *
#1300
b0 !
b0 4
1&
#1400
0&
#1450
b11111111111111111111111111111111 ,
