sequential-logic/memory/single_port_ram_synchronous/single_port_ram_synchronous.v
// Single-port synchronous RAM.

module single_port_ram_synchronous_behavioral(
    input  clk,                   // Clock
    input  we,                    // Write enable
    input  [3:0] addr,            // Address
    input  [7:0] data_in,         // Data to write
    output [7:0] data_out);       // Data to read

    // DATA TYPES
    reg [7:0] mem [0:15];         //RAM
    reg [3:0] address_register;

    // OUTPUT (THIS MAKES IT SYNCHRONOUS)
    assign data_out = mem[address_register];

    // RAM
    // ALWAYS BLOCK with NON-BLOCKING PROCEDURAL ASSIGNMENT STATEMENT
    always @(posedge clk) begin
        if (we) begin
            mem[addr] <= data_in;
        end else begin
            address_register <= addr;
        end
    end

endmodule

sequential-logic/memory/single_port_ram_synchronous/single_port_ram_synchronous_tb.v
`timescale 1ns / 100ps // time-unit = 1 ns, precision = 100 ps

// include files in single_port_ram_synchronous.vh

module SINGLE_PORT_RAM_SYNCHRONOUS_TB;

    // DATA TYPES - DECLARE REGISTERS AND WIRES (PROBES)
    reg             CLK;
    reg             WE;
    reg  [3:0]      ADDR;
    reg  [7:0]      DATA_IN;
    wire [7:0]      DATA_OUT;
  
    // FOR TESTING  
    reg [31:0]      VECTORCOUNT, ERRORS;
    reg [7:0]       DATA_OUTEXP;
    integer         FD, COUNT;
    reg [8*32-1:0]  COMMENT;

    // UNIT UNDER TEST
    single_port_ram_synchronous_behavioral UUT_single_port_ram_synchronous_behavioral(
        .clk (CLK),
        .we (WE),
        .addr (ADDR),
        .data_in (DATA_IN),
        .data_out (DATA_OUT)
    );

    // SAVE EVERYTHING FROM TOP TB MODULE IN A DUMP FILE
    initial begin
        $dumpfile("single_port_ram_synchronous_tb.vcd");
        $dumpvars(0, SINGLE_PORT_RAM_SYNCHRONOUS_TB);
    end

    // CLK PERIOD
    localparam CLKPERIOD = 20;

    // CLK
    always begin
        #(CLKPERIOD/2) CLK = ~CLK;
    end

    // INITIALIZE TESTBENCH
    initial begin

        // OPEN VECTOR FILE - THROW AWAY FIRST LINE
        FD=$fopen("single_port_ram_synchronous_tb.tv","r");
        COUNT = $fscanf(FD, "%s", COMMENT);
        // $display ("FIRST LINE IS: %s", COMMENT);

        // INIT TESTBENCH
        COUNT = $fscanf(FD, "%s %b %b %b %b", COMMENT, WE, ADDR, DATA_IN, DATA_OUTEXP);
        CLK = 0;
        VECTORCOUNT = 0;
        ERRORS = 0;

        // DISPAY OUTPUT AND MONITOR
        $display();
        $display("TEST START --------------------------------");
        $display();
        $display("                 | TIME(ns) | WE | ADDR | DATA_IN | DATA_OUT |");
        $display("                 ---------------------------------------------");
        $monitor("%4d  %10s | %8d | %1b | %1b |   %1b   |   %1b   |", VECTORCOUNT, COMMENT, $time, WE, ADDR, DATA_IN, DATA_OUT);

    end

    // APPLY TEST VECTORS ON NEG EDGE CLK (ADD DELAY)
    always @(negedge CLK) begin

        // WAIT A BIT (AFTER CHECK)
        #5;

        // GET VECTORS FROM TB FILE
        COUNT = $fscanf(FD, "%s %b %b %b %b", COMMENT, WE, ADDR, DATA_IN, DATA_OUTEXP);

        // CHECK IF EOF - PRINT SUMMARY, CLOSE VECTOR FILE AND FINISH TB
        if (COUNT == -1) begin
            $fclose(FD);
            $display();
            $display(" VECTORS: %4d", VECTORCOUNT);
            $display("  ERRORS: %4d", ERRORS);
            $display();
            $display("TEST END ----------------------------------");
            $display();
            $finish;
        end

        // GET ANOTHER VECTOR
        VECTORCOUNT = VECTORCOUNT + 1;

    end

    // CHECK TEST VECTORS ON POS EGDE CLK
    always @(posedge CLK) begin

        // WAIT A BIT
        #5;

        // CHECK EACH VECTOR RESULT
        if (DATA_OUTEXP !== DATA_OUT) begin
            $display("***ERROR - Expected DATA_OUT=%b", DATA_OUTEXP);
            ERRORS = ERRORS + 1;
        end

    end   

endmodule

sequential-logic/memory/single_port_ram_synchronous/single_port_ram_synchronous_tb.vcd
$date
	Sun May 14 00:23:06 2023
$end
$version
	Icarus Verilog
$end
$timescale
	100ps
$end
$scope module SINGLE_PORT_RAM_SYNCHRONOUS_TB $end
$var wire 8 ! DATA_OUT [7:0] $end
$var parameter 32 " CLKPERIOD $end
$var reg 4 # ADDR [3:0] $end
$var reg 1 $ CLK $end
$var reg 256 % COMMENT [255:0] $end
$var reg 8 & DATA_IN [7:0] $end
$var reg 8 ' DATA_OUTEXP [7:0] $end
$var reg 32 ( ERRORS [31:0] $end
$var reg 32 ) VECTORCOUNT [31:0] $end
$var reg 1 * WE $end
$var integer 32 + COUNT [31:0] $end
$var integer 32 , FD [31:0] $end
$scope module UUT_single_port_ram_synchronous_behavioral $end
$var wire 4 - addr [3:0] $end
$var wire 1 $ clk $end
$var wire 8 . data_in [7:0] $end
$var wire 8 / data_out [7:0] $end
$var wire 1 * we $end
$var reg 4 0 address_register [3:0] $end
$upscope $end
$upscope $end
$enddefinitions $end
$comment Show the parameter values. $end
$dumpall
b10100 "
$end
#0
$dumpvars
bx 0
bx /
b0 .
b0 -
b10000000000000000000000000000011 ,
b101 +
1*
b0 )
b0 (
bx '
b0 &
b1001001010011100100100101010100 %
0$
b0 #
bx !
$end
#100
1$
#200
0$
#250
b1 )
b11110000 &
b11110000 .
b101011101010010010010010101010001000101 %
#300
1$
#400
0$
#450
b10 )
b1111 &
b1111 .
b1 #
b1 -
#500
1$
#600
0$
#650
b11 )
b10101010 &
b10101010 .
b1110 #
b1110 -
#700
1$
#800
0$
#850
b100 )
b11110000 '
bx &
bx .
b0 #
b0 -
0*
b1010010010001010100000101000100 %
#900
b11110000 !
b11110000 /
b0 0
1$
#1000
0$
#1050
b101 )
b1111 '
b1 #
b1 -
#1100
b1111 !
b1111 /
b1 0
1$
#1200
0$
#1250
b110 )
b10101010 '
b1110 #
b1110 -
#1300
b10101010 !
b10101010 /
b1110 0
1$
#1400
0$
#1450
b111 )
b111 &
b111 .
b1001 #
b1001 -
1*
b101011101010010010010010101010001000101 %
#1500
1$
#1600
0$
#1650
b1000 )
b11111010 &
b11111010 .
b1111 #
b1111 -
#1700
1$
#1800
0$
#1850
b1001 )
b11 &
b11 .
b1100 #
b1100 -
#1900
1$
#2000
0$
#2050
b1010 )
b1111 &
b1111 .
b10 #
b10 -
#2100
1$
#2200
0$
#2250
b1011 )
b1111 '
bx &
bx .
b1 #
b1 -
0*
b1010010010001010100000101000100 %
#2300
b1111 !
b1111 /
b1 0
1$
#2400
0$
#2450
b1100 )
b11111010 '
b1111 #
b1111 -
#2500
b11111010 !
b11111010 /
b1111 0
1$
#2600
0$
#2650
b11111111111111111111111111111111 +
