combinational-logic/multiplexers-and-demultiplexers/demux_1x4/demux_1x4.v
// Demultiplexer - One input, four outputs (using a case statement).

module demux_1x4(
    input       y,               // 1 Input
    input       [1:0] sel,       // Select
    output reg  a, b, c, d       // 4 Outputs
);

    // DEMULTIPLEXER
    always @ ( * ) begin
        case(sel)
            2'b00 : begin
                a <= y; b <= 0; c <= 0; d <= 0;
            end
            2'b01 : begin
                a <= 0; b <= y; c <= 0; d <= 0;
            end
            2'b10 : begin
                a <= 0; b <= 0; c <= y; d <= 0;
            end
            2'b11 : begin
                a <= 0; b <= 0; c <= 0; d <= y;
            end
        endcase
    end

endmodule

combinational-logic/multiplexers-and-demultiplexers/mux-4x1/mux-4x1.v
// 4x1 multiplexer
module mux_4x1(
    input  a, b, c, d,      // 4 Inputs
    input  [1:0] sel,       // Select
    output y                // 1 Output
);

reg  y;

always @ ( * ) begin
    case(sel)
        2'b00 : y <= a;
        2'b01 : y <= b;
        2'b10 : y <= c;
        2'b11 : y <= d;
    endcase
 end

endmodule

combinational-logic/multiplexers-and-demultiplexers/mux-to-demux/mux-to-demux.v
// multiplexer to demultiplexer

module mux_to_demux(
    input  a_in, b_in, c_in, d_in,      // 4 Inputs
    input  [1:0] sel,                   // Select
    output a_out, b_out, c_out, d_out   // 4 Outputs
);

wire  y;

mux_4x1 MUX_4X1 (
    .a(a_in), .b(b_in), .c(c_in), .d(d_in),
    .sel(sel),
    .y(y)
);

demux_1x4 DEMUX_1X4 (
    .y(y),
    .sel(sel),
    .a(a_out), .b(b_out), .c(c_out), .d(d_out)
);

endmodule

combinational-logic/multiplexers-and-demultiplexers/mux-to-demux/mux-to-demux-tb.v
`timescale 1ns / 1ns
`include "mux-to-demux.v"

module mux_to_demux_tb;

// DATA TYPES - DECLAIR INPUTS AND OUTPUTS
reg     A_IN, B_IN, C_IN, D_IN;
reg     [1:0] SEL;
wire    A_OUT, B_OUT, C_OUT, D_OUT;
integer i;

// UUT
mux_to_demux uut(
    .a_in(A_IN), .b_in(B_IN), .c_in(C_IN), .d_in(D_IN),
    .sel(SEL),
    .a_out(A_OUT), .b_out(B_OUT), .c_out(C_OUT), .d_out(D_OUT)
);

// FILES
initial begin
    $dumpfile("mux-to-demux-tb.vcd");
    $dumpvars(0, mux_to_demux_tb);
end

// TESTCASE
initial begin
    $display("test start");
    A_IN = 0; B_IN = 0; C_IN = 0; D_IN = 0;
    SEL = 2'b00;

    for (i = 0; i < 64; i = i + 1) begin
        {SEL, D_IN, C_IN, B_IN, A_IN} = i;
        #10;
    end
    
    $display("test complete");
    $finish;
end

endmodule

combinational-logic/multiplexers-and-demultiplexers/mux-to-demux/mux-to-demux-tb.vcd
$date
	Tue Oct 27 09:41:36 2020
$end
$version
	Icarus Verilog
$end
$timescale
	1ns
$end
$scope module mux_to_demux_tb $end
$var wire 1 ! D_OUT $end
$var wire 1 " C_OUT $end
$var wire 1 # B_OUT $end
$var wire 1 $ A_OUT $end
$var reg 1 % A_IN $end
$var reg 1 & B_IN $end
$var reg 1 ' C_IN $end
$var reg 1 ( D_IN $end
$var reg 2 ) SEL [1:0] $end
$var integer 32 * i [31:0] $end
$scope module uut $end
$var wire 1 % a_in $end
$var wire 1 & b_in $end
$var wire 1 ' c_in $end
$var wire 1 ( d_in $end
$var wire 2 + sel [1:0] $end
$var wire 1 , y $end
$var wire 1 ! d_out $end
$var wire 1 " c_out $end
$var wire 1 # b_out $end
$var wire 1 $ a_out $end
$scope module DEMUX_1X4 $end
$var wire 2 - sel [1:0] $end
$var wire 1 , y $end
$var reg 1 $ a $end
$var reg 1 # b $end
$var reg 1 " c $end
$var reg 1 ! d $end
$upscope $end
$scope module MUX_4X1 $end
$var wire 1 % a $end
$var wire 1 & b $end
$var wire 1 ' c $end
$var wire 1 ( d $end
$var wire 2 . sel [1:0] $end
$var reg 1 , y $end
$upscope $end
$upscope $end
$upscope $end
$enddefinitions $end
#0
$dumpvars
b0 .
b0 -
0,
b0 +
b0 *
b0 )
0(
0'
0&
0%
0$
0#
0"
0!
$end
#10
1$
1,
1%
b1 *
#20
0$
0,
1&
0%
b10 *
#30
1$
1,
1%
b11 *
#40
0$
0,
1'
0&
0%
b100 *
#50
1$
1,
1%
b101 *
#60
0$
0,
1&
0%
b110 *
#70
1$
1,
1%
b111 *
#80
0$
0,
1(
0'
0&
0%
b1000 *
#90
1$
1,
1%
b1001 *
#100
0$
0,
1&
0%
b1010 *
#110
1$
1,
1%
b1011 *
#120
0$
0,
1'
0&
0%
b1100 *
#130
1$
1,
1%
b1101 *
#140
0$
0,
1&
0%
b1110 *
#150
1$
1,
1%
b1111 *
#160
0#
0$
0,
b1 )
b1 +
b1 -
b1 .
0(
0'
0&
0%
b10000 *
#170
1%
b10001 *
#180
1#
1,
1&
0%
b10010 *
#190
1%
b10011 *
#200
0#
0,
1'
0&
0%
b10100 *
#210
1%
b10101 *
#220
1#
1,
1&
0%
b10110 *
#230
1%
b10111 *
#240
0#
0,
1(
0'
0&
0%
b11000 *
#250
1%
b11001 *
#260
1#
1,
1&
0%
b11010 *
#270
1%
b11011 *
#280
0#
0,
1'
0&
0%
b11100 *
#290
1%
b11101 *
#300
1#
1,
1&
0%
b11110 *
#310
1%
b11111 *
#320
0"
0#
0,
b10 )
b10 +
b10 -
b10 .
0(
0'
0&
0%
b100000 *
#330
1%
b100001 *
#340
1&
0%
b100010 *
#350
1%
b100011 *
#360
1"
1,
1'
0&
0%
b100100 *
#370
1%
b100101 *
#380
1&
0%
b100110 *
#390
1%
b100111 *
#400
0"
0,
1(
0'
0&
0%
b101000 *
#410
1%
b101001 *
#420
1&
0%
b101010 *
#430
1%
b101011 *
#440
1"
1,
1'
0&
0%
b101100 *
#450
1%
b101101 *
#460
1&
0%
b101110 *
#470
1%
b101111 *
#480
0!
0"
0,
b11 )
b11 +
b11 -
b11 .
0(
0'
0&
0%
b110000 *
#490
1%
b110001 *
#500
1&
0%
b110010 *
#510
1%
b110011 *
#520
1'
0&
0%
b110100 *
#530
1%
b110101 *
#540
1&
0%
b110110 *
#550
1%
b110111 *
#560
1!
1,
1(
0'
0&
0%
b111000 *
#570
1%
b111001 *
#580
1&
0%
b111010 *
#590
1%
b111011 *
#600
1'
0&
0%
b111100 *
#610
1%
b111101 *
#620
1&
0%
b111110 *
#630
1%
b111111 *
#640
b1000000 *
