combinational-logic/multiplexers-and-demultiplexers/jeff_74x151/jeff_74x151.v
// 8-line to 1-line data selector/multiplexer.
// Based on the 7400-series integrated circuits used in my programable-8-bit-microprocessor.
   
module jeff_74x151_behavioral(
    input                d0,                  // DATA IN
    input                d1,                  // 
    input                d2,                  // 
    input                d3,                  // 
    input                d4,                  // 
    input                d5,                  // 
    input                d6,                  // 
    input                d7,                  // 
    input                a,                   // SELECT
    input                b,                   // 
    input                c,                   // 
    input                en,                  // ENABLE
    output reg           y,                   // DATA OUT
    output               w                    // INVERTED OUTPUT
);

    assign w = ~y;

    // ALWAYS BLOCK with NON-BLOCKING PROCEDURAL ASSIGNMENT STATEMENT
    always @ ( * ) begin
        if (en) begin
            case({c,b,a})
                3'b000 : y <= d0;
                3'b001 : y <= d1;
                3'b010 : y <= d2;
                3'b011 : y <= d3;
                3'b100 : y <= d4;
                3'b101 : y <= d5;
                3'b110 : y <= d6;
                3'b111 : y <= d7;
            endcase
        end else begin
            y <= 1'b1;
        end
    end

endmodule

combinational-logic/multiplexers-and-demultiplexers/jeff_74x151/jeff_74x151_tb.v
`timescale 1ns / 100ps // time-unit = 1 ns, precision = 100 ps

// include files are in jeff_74x151.vh

module JEFF_74x151_TB;

    // DATA TYPES - DECLARE REGISTERS AND WIRES (PROBES)
    reg  [7:0]      D;
    reg  [2:0]      SEL;
    reg             EN;
    wire            Y;
    wire            W;

    // FOR TESTING  
    reg             TICK;
    reg [31:0]      VECTORCOUNT, ERRORS;
    reg             YEXPECTED;
    integer         FD, COUNT;
    reg [8*32-1:0]  COMMENT;

    // UNIT UNDER TEST (behavioral)
    jeff_74x151_behavioral UUT_jeff_74x151_behavioral(
        .d0(D[0]), .d1(D[1]), .d2(D[2]), .d3(D[3]), .d4(D[4]), .d5(D[5]), .d6(D[6]), .d7(D[7]),
        .a(SEL[0]), .b(SEL[1]), .c(SEL[2]),
        .en(EN),
        .y(Y), .w(W)
    );

    // SAVE EVERYTHING FROM TOP TB MODULE IN A DUMP FILE
    initial begin
        $dumpfile("jeff_74x151_tb.vcd");
        $dumpvars(0, JEFF_74x151_TB);
    end

    // TICK PERIOD
    localparam TICKPERIOD = 20;

    // TICK
    always begin
        #(TICKPERIOD/2) TICK = ~TICK;
    end

    // INITIALIZE TESTBENCH
    initial begin

        // OPEN VECTOR FILE - THROW AWAY FIRST LINE
        FD=$fopen("jeff_74x151_tb.tv","r");
        COUNT = $fscanf(FD, "%s", COMMENT);
        // $display ("FIRST LINE IS: %s", COMMENT);

        // INIT TESTBENCH
        COUNT = $fscanf(FD, "%s %b %b %b %b", COMMENT, EN, SEL, D, YEXPECTED);
        TICK = 0;
        VECTORCOUNT = 1;
        ERRORS = 0;

        // DISPAY OUTPUT AND MONITOR
        $display();
        $display("TEST START --------------------------------");
        $display();
        $display("                 | TIME(ns) | EN | SEL | D        | Y |");
        $display("                 --------------------------------------");
        // $monitor("%4d  %10s | %8d | %1b  | %1b | %1b | %1b |", VECTORCOUNT, COMMENT, $time, EN, SEL, D, Y);

    end

    // APPLY TEST VECTORS ON NEG EDGE TICK (ADD DELAY)
    always @(negedge TICK) begin

        // WAIT A BIT (AFTER CHECK)
        #5;

        // GET VECTORS FROM TB FILE
        COUNT = $fscanf(FD, "%s %b %b %b %b", COMMENT, EN, SEL, D, YEXPECTED);

        // CHECK IF EOF - PRINT SUMMARY, CLOSE VECTOR FILE AND FINISH TB
        if (COUNT == -1) begin
            $fclose(FD);
            $display();
            $display(" VECTORS: %4d", VECTORCOUNT);
            $display("  ERRORS: %4d", ERRORS);
            $display();
            $display("TEST END ----------------------------------");
            $display();
            $finish;
        end

        // GET ANOTHER VECTOR
        VECTORCOUNT = VECTORCOUNT + 1;

    end

    // CHECK TEST VECTORS ON POS EGDE TICK
    always @(posedge TICK) begin

        // WAIT A BIT
        #5;

        // DISPLAY OUTPUT ON POS EDGE TICK
        $display("%4d  %10s | %8d | %1b  | %1b | %1b | %1b |", VECTORCOUNT, COMMENT, $time, EN, SEL, D, Y);

        // CHECK EACH VECTOR RESULT
        if (Y !== YEXPECTED) begin
            $display("***ERROR (behavioral) - Expected Y = %b", YEXPECTED);
            ERRORS = ERRORS + 1;
        end

    end   

endmodule

combinational-logic/multiplexers-and-demultiplexers/jeff_74x151/jeff_74x151_tb.vcd
$date
	Sat May 20 18:02:43 2023
$end
$version
	Icarus Verilog
$end
$timescale
	100ps
$end
$scope module JEFF_74x151_TB $end
$var wire 1 ! Y $end
$var wire 1 " W $end
$var parameter 32 # TICKPERIOD $end
$var reg 256 $ COMMENT [255:0] $end
$var reg 8 % D [7:0] $end
$var reg 1 & EN $end
$var reg 32 ' ERRORS [31:0] $end
$var reg 3 ( SEL [2:0] $end
$var reg 1 ) TICK $end
$var reg 32 * VECTORCOUNT [31:0] $end
$var reg 1 + YEXPECTED $end
$var integer 32 , COUNT [31:0] $end
$var integer 32 - FD [31:0] $end
$scope module UUT_jeff_74x151_behavioral $end
$var wire 1 . a $end
$var wire 1 / b $end
$var wire 1 0 c $end
$var wire 1 1 d0 $end
$var wire 1 2 d1 $end
$var wire 1 3 d2 $end
$var wire 1 4 d3 $end
$var wire 1 5 d4 $end
$var wire 1 6 d5 $end
$var wire 1 7 d6 $end
$var wire 1 8 d7 $end
$var wire 1 & en $end
$var wire 1 " w $end
$var reg 1 ! y $end
$upscope $end
$upscope $end
$enddefinitions $end
$comment Show the parameter values. $end
$dumpall
b10100 #
$end
#0
$dumpvars
x8
x7
x6
x5
x4
x3
x2
x1
x0
x/
x.
b10000000000000000000000000000011 -
b101 ,
1+
b1 *
0)
bx (
b0 '
0&
bx %
b1001001010011100100100101010100 $
0"
1!
$end
#100
1)
#200
0)
#250
0.
0/
00
b10 *
b0 (
b101101 $
#300
1)
#400
0)
#450
1"
0!
01
b11 *
0+
bx0 %
1&
#500
1)
#600
0)
#650
0"
1!
11
b100 *
1+
bx1 %
#700
1)
#800
0)
#850
1"
0!
x1
02
1.
b101 *
0+
bx0x %
b1 (
#900
1)
#1000
0)
#1050
0"
1!
12
b110 *
1+
bx1x %
#1100
1)
#1200
0)
#1250
1"
0!
x2
03
0.
1/
b111 *
0+
bx0xx %
b10 (
#1300
1)
#1400
0)
#1450
0"
1!
13
b1000 *
1+
bx1xx %
#1500
1)
#1600
0)
#1650
1"
0!
x3
04
1.
b1001 *
0+
bx0xxx %
b11 (
#1700
1)
#1800
0)
#1850
0"
1!
14
b1010 *
1+
bx1xxx %
#1900
1)
#2000
0)
#2050
1"
0!
x4
05
0.
0/
10
b1011 *
0+
bx0xxxx %
b100 (
#2100
1)
#2200
0)
#2250
0"
1!
15
b1100 *
1+
bx1xxxx %
#2300
1)
#2400
0)
#2450
1"
0!
x5
06
1.
b1101 *
0+
bx0xxxxx %
b101 (
#2500
1)
#2600
0)
#2650
0"
1!
16
b1110 *
1+
bx1xxxxx %
#2700
1)
#2800
0)
#2850
1"
0!
x6
07
0.
1/
b1111 *
0+
bx0xxxxxx %
b110 (
#2900
1)
#3000
0)
#3050
0"
1!
17
b10000 *
1+
bx1xxxxxx %
#3100
1)
#3200
0)
#3250
1"
0!
x7
08
1.
b10001 *
0+
b0xxxxxxx %
b111 (
#3300
1)
#3400
0)
#3450
0"
1!
18
b10010 *
1+
b1xxxxxxx %
#3500
1)
#3600
0)
#3650
b11111111111111111111111111111111 ,
