combinational-logic/data-operators/full_adder/full_adder.v
// A 2-bit full adder

module full_adder_gate(
    input       a,           // Data
    input       b,           // Data
    input       cin,         // Carry in
    output      sum,         // Sum of a + b
    output      cout);       // Carry out

    wire        w1, w2, w3;

    xor         xor1(w1, a, b);
    xor         xor2(sum, w1, cin);
    and         and1(w2, w1, cin);
    and         and2(w3, a, b);
    or          or1(cout, w2, w3);

endmodule

module full_adder_dataflow(
    input       a,           // Data
    input       b,           // Data
    input       cin,         // Carry in
    output      sum,         // Sum of a + b
    output      cout);       // Carry out

    assign sum  = a ^ b ^ cin;
    assign cout = (a & b) | (cin & (a ^ b));

endmodule

module full_adder_behavioral(
    input       a,           // Data
    input       b,           // Data
    input       cin,         // Carry in
    output reg  sum,         // Sum of a + b
    output reg  cout);       // Carry out

    always @ ( a or b or cin) begin
        {cout, sum} <= a + b + cin;
    end

endmodule

combinational-logic/data-operators/full_adder/full_adder_tb.v
`timescale 1ns / 100ps // time-unit = 1 ns, precision = 100 ps

// include files are in full_adder.vh

module FULL_ADDER_TB;

    // DATA TYPES - DECLARE REGISTERS AND WIRES (PROBES)
    reg             A, B;
    reg             CIN;
    wire            SUM_gate, SUM_data, SUM_beh;
    wire            COUT_gate, COUT_data, COUT_beh;

    // FOR TESTING  
    reg             TICK;
    reg [31:0]      VECTORCOUNT, ERRORS;
    reg             COUTEXPECTED, SUMEXPECTED;
    integer         FD, COUNT;
    reg [8*32-1:0]  COMMENT;

    // UNIT UNDER TEST (gate)
    full_adder_gate UUT_full_adder_gate(
        .a(A), .b(B),
        .cin(CIN),
        .sum(SUM_gate),
        .cout(COUT_gate)
    );

    // UNIT UNDER TEST (dataflow)
    full_adder_dataflow UUT_full_adder_dataflow(
        .a(A), .b(B),
        .cin(CIN),
        .sum(SUM_data),
        .cout(COUT_data)
    );

    // UNIT UNDER TEST (behavioral)
    full_adder_behavioral UUT_full_adder_behavioral(
        .a(A), .b(B),
        .cin(CIN),
        .sum(SUM_beh),
        .cout(COUT_beh)
    );

    // SAVE EVERYTHING FROM TOP TB MODULE IN A DUMP FILE
    initial begin
        $dumpfile("full_adder_tb.vcd");
        $dumpvars(0, FULL_ADDER_TB);
    end

    // TICK PERIOD
    localparam TICKPERIOD = 20;

    // TICK
    always begin
        #(TICKPERIOD/2) TICK = ~TICK;
    end

    // INITIALIZE TESTBENCH
    initial begin

        // OPEN VECTOR FILE - THROW AWAY FIRST LINE
        FD=$fopen("full_adder_tb.tv","r");
        COUNT = $fscanf(FD, "%s", COMMENT);
        // $display ("FIRST LINE IS: %s", COMMENT);

        // INIT TESTBENCH
        COUNT = $fscanf(FD, "%s %b %b %b %b %b", COMMENT, A, B, CIN, SUMEXPECTED, COUTEXPECTED);
        TICK = 0;
        VECTORCOUNT = 0;
        ERRORS = 0;

        // DISPAY OUTPUT AND MONITOR
        $display();
        $display("TEST START --------------------------------");
        $display();
        $display("                                            GATE -----   DATA -----   BEH ------");
        $display("                 | TIME(ns) | A | B | CIN | SUM | COUT | SUM | COUT | SUM | COUT |");
        $display("                 -----------------------------------------------------------------");
        $monitor("%4d  %10s | %8d |  %1d  | %1d | %1d |  %1d   |  %1d  |  %1d   |  %1d  |  %1d   |  %1d  |", VECTORCOUNT, COMMENT, $time, A, B, CIN, SUM_gate, COUT_gate, SUM_data, COUT_data, SUM_beh, SUM_beh);

    end

    // APPLY TEST VECTORS ON NEG EDGE TICK (ADD DELAY)
    always @(negedge TICK) begin

        // WAIT A BIT (AFTER CHECK)
        #5;

        // GET VECTORS FROM TB FILE
        COUNT = $fscanf(FD, "%s %b %b %b %b %b", COMMENT, A, B, CIN, SUMEXPECTED, COUTEXPECTED);

        // CHECK IF EOF - PRINT SUMMARY, CLOSE VECTOR FILE AND FINISH TB
        if (COUNT == -1) begin
            $fclose(FD);
            $display();
            $display(" VECTORS: %4d", VECTORCOUNT);
            $display("  ERRORS: %4d", ERRORS);
            $display();
            $display("TEST END ----------------------------------");
            $display();
            $finish;
        end

        // GET ANOTHER VECTOR
        VECTORCOUNT = VECTORCOUNT + 1;

    end

    // CHECK TEST VECTORS ON POS EGDE TICK
    always @(posedge TICK) begin

        // WAIT A BIT
        #5;

        // CHECK EACH VECTOR RESULT
        if ((SUM_gate !== SUMEXPECTED) | (COUT_gate !== COUTEXPECTED)) begin
            $display("***ERROR (gate) - Expected SUM=%b COUT=%b", SUMEXPECTED, COUTEXPECTED);
            ERRORS = ERRORS + 1;
        end
        if ((SUM_data !== SUMEXPECTED) | (COUT_data !== COUTEXPECTED)) begin
            $display("***ERROR (dataflow) - Expected SUM=%b COUT=%b", SUMEXPECTED, COUTEXPECTED);
            ERRORS = ERRORS + 1;
        end
        if ((SUM_beh !== SUMEXPECTED) | (COUT_beh !== COUTEXPECTED)) begin
            $display("***ERROR (behavioral) - Expected SUM=%b COUT=%b", SUMEXPECTED, COUTEXPECTED);
            ERRORS = ERRORS + 1;
        end

    end   

endmodule

combinational-logic/data-operators/full_adder/full_adder_tb.vcd
$date
	Thu May  4 00:04:37 2023
$end
$version
	Icarus Verilog
$end
$timescale
	100ps
$end
$scope module FULL_ADDER_TB $end
$var wire 1 ! SUM_gate $end
$var wire 1 " SUM_data $end
$var wire 1 # SUM_beh $end
$var wire 1 $ COUT_gate $end
$var wire 1 % COUT_data $end
$var wire 1 & COUT_beh $end
$var parameter 32 ' TICKPERIOD $end
$var reg 1 ( A $end
$var reg 1 ) B $end
$var reg 1 * CIN $end
$var reg 256 + COMMENT [255:0] $end
$var reg 1 , COUTEXPECTED $end
$var reg 32 - ERRORS [31:0] $end
$var reg 1 . SUMEXPECTED $end
$var reg 1 / TICK $end
$var reg 32 0 VECTORCOUNT [31:0] $end
$var integer 32 1 COUNT [31:0] $end
$var integer 32 2 FD [31:0] $end
$scope module UUT_full_adder_behavioral $end
$var wire 1 ( a $end
$var wire 1 ) b $end
$var wire 1 * cin $end
$var reg 1 & cout $end
$var reg 1 # sum $end
$upscope $end
$scope module UUT_full_adder_dataflow $end
$var wire 1 ( a $end
$var wire 1 ) b $end
$var wire 1 * cin $end
$var wire 1 % cout $end
$var wire 1 " sum $end
$upscope $end
$scope module UUT_full_adder_gate $end
$var wire 1 ( a $end
$var wire 1 ) b $end
$var wire 1 * cin $end
$var wire 1 $ cout $end
$var wire 1 ! sum $end
$var wire 1 3 w1 $end
$var wire 1 4 w2 $end
$var wire 1 5 w3 $end
$upscope $end
$upscope $end
$enddefinitions $end
$comment Show the parameter values. $end
$dumpall
b10100 '
$end
#0
$dumpvars
05
04
03
b10000000000000000000000000000011 2
b110 1
b0 0
0/
0.
b0 -
0,
b1001001010011100100100101010100 +
0*
0)
0(
0&
0%
0$
0#
0"
0!
$end
#100
1/
#200
0/
#250
b1 0
b101101 +
#300
1/
#400
0/
#450
1#
1"
1!
b10 0
1.
1*
#500
1/
#600
0/
#650
13
b11 0
0*
1)
#700
1/
#800
0/
#850
1&
0#
1%
1$
0"
0!
14
b100 0
1,
0.
1*
#900
1/
#1000
0/
#1050
0&
1#
0%
0$
1"
1!
04
b101 0
0,
1.
0*
0)
1(
#1100
1/
#1200
0/
#1250
1&
0#
1%
1$
0"
0!
14
b110 0
1,
0.
1*
#1300
1/
#1400
0/
#1450
04
03
15
b111 0
0*
1)
#1500
1/
#1600
0/
#1650
1#
1"
1!
b1000 0
1.
1*
#1700
1/
#1800
0/
#1850
b11111111111111111111111111111111 1
