combinational-logic/data-operators/full_adder/full_adder.v
// A 2-bit full adder

module full_adder(
    input       a,           // Data
    input       b,           // Data
    input       cin,         // Carry in
    output reg  sum,         // Sum of a + b
    output reg  cout         // Carry out
);

    // ADDER
    always @ ( a or b or cin) begin
        {cout, sum} <= a + b + cin;
    end

endmodule

combinational-logic/data-operators/full_adder/full_adder_tb.v
`timescale 1ns / 1ns

// include files in full-adder.vh

module full_adder_tb;

    // DATA TYPES - DECLARE REGISTERS AND WIRES (PROBES)
    reg     A, B, CIN;
    wire    SUM, COUT;
    integer i;

    // UNIT UNDER TEST
    full_adder uut(
        .a(A), .b(B), .cin(CIN),
        .sum(SUM), .cout(COUT)
    );

    // SAVE EVERYTHING FROM TOP MODULE IN A DUMP FILE
    initial begin
        $dumpfile("full_adder_tb.vcd");
        $dumpvars(0, full_adder_tb);
    end

    // TESTCASE - CHANGE REG VALUES
    initial begin
        $display("test start");
        A = 0;
        B = 0;
        CIN = 0;

        for (i = 0; i < 8; i = i + 1) begin
            {A, B, CIN} = i;
            #10;
        end
        
        $display("test complete");
        $finish;
    end

endmodule

combinational-logic/data-operators/full_adder/full-adder-tb.vcd
$date
	Wed Nov 11 20:15:53 2020
$end
$version
	Icarus Verilog
$end
$timescale
	1ns
$end
$scope module full_adder_tb $end
$var wire 1 ! SUM $end
$var wire 1 " COUT $end
$var reg 1 # A $end
$var reg 1 $ B $end
$var reg 1 % CIN $end
$var integer 32 & i [31:0] $end
$scope module uut $end
$var wire 1 # a $end
$var wire 1 $ b $end
$var wire 1 % cin $end
$var reg 1 " cout $end
$var reg 1 ! sum $end
$upscope $end
$upscope $end
$enddefinitions $end
#0
$dumpvars
b0 &
0%
0$
0#
0"
0!
$end
#10
1!
1%
b1 &
#20
1$
0%
b10 &
#30
1"
0!
1%
b11 &
#40
0"
1!
1#
0$
0%
b100 &
#50
1"
0!
1%
b101 &
#60
1$
0%
b110 &
#70
1!
1%
b111 &
#80
b1000 &
