basic-code/sequential-logic/d-flip-flop/d-flip-flop.v
// A positive edge d flip-flop with asynchronous enable.

module d_flip_flop (
    input       clk,        // Clock
    input       en,         // Enable
    input       d,          // Input
    output reg  q,          // Output
    output      q_bar       //
);

assign q_bar = ~q;

// D FLIP-FLOP WITH ASYNC ENABLE
always @ (posedge clk or posedge en) begin
    if (en) begin
        q <= d;
    end else begin
        q <= q;
    end
end

endmodule

basic-code/sequential-logic/d-flip-flop/d-flip-flop-tb.v
`timescale 1ns / 1ns
`include "d-flip-flop.v"

module d_flip_flop_tb;

// DATA TYPES - DECLAIR INPUTS AND OUTPUTS
reg  CLK;
reg  EN;
reg  D;
wire Q, Q_BAR;

// UUT
d_flip_flop uut(
    .clk(CLK),
    .en(EN),
    .d(D),
    .q(Q), .q_bar(Q_BAR)
);

// FILES
initial begin
    $dumpfile("d-flip-flop-tb.vcd");
    $dumpvars(0, d_flip_flop_tb);
end

// CLOCK
always begin
    #10 CLK = ~CLK;
end

// TESTCASE
initial begin
    $display("test start");
    CLK = 0;
    EN = 0;
    D = 0;
    
    // ENABLE
    #15; EN = 1;
    #20  D = 1;
    #20; D = 0;
    #20; D = 1;
    #20; D = 0;
    #10; D = 0;

    // STOP ENABLE - KEEPS STATE REGARDLESS OF INPUT
    #20; EN = 0;
    #10  D = 1;
    #20; D = 0;
    #10; D = 1;
    #20

    $display("test complete");
    $finish;
end

endmodule

basic-code/sequential-logic/d-flip-flop/d-flip-flop-tb.vcd
$date
	Mon Nov  2 14:41:56 2020
$end
$version
	Icarus Verilog
$end
$timescale
	1ns
$end
$scope module d_flip_flop_tb $end
$var wire 1 ! Q_BAR $end
$var wire 1 " Q $end
$var reg 1 # CLK $end
$var reg 1 $ D $end
$var reg 1 % EN $end
$scope module uut $end
$var wire 1 # clk $end
$var wire 1 $ d $end
$var wire 1 % en $end
$var wire 1 ! q_bar $end
$var reg 1 " q $end
$upscope $end
$upscope $end
$enddefinitions $end
#0
$dumpvars
0%
0$
0#
x"
x!
$end
#10
1#
#15
1!
0"
1%
#20
0#
#30
1#
#35
1$
#40
0#
#50
0!
1"
1#
#55
0$
#60
0#
#70
1!
0"
1#
#75
1$
#80
0#
#90
0!
1"
1#
#95
0$
#100
0#
#110
1!
0"
1#
#120
0#
#125
0%
#130
1#
#135
1$
#140
0#
#150
1#
#155
0$
#160
0#
#165
1$
