combinational-logic/multiplexers-and-demultiplexers/jeff-74x151/jeff-74x151.v
// 8-line to 1-line data selector/multiplexer
module jeff_74x151(
    input                d0,                  // 
    input                d1,                  // 
    input                d2,                  // 
    input                d3,                  // 
    input                d4,                  // 
    input                d5,                  // 
    input                d6,                  // 
    input                d7,                  // 
    input                a,                  // 
    input                b,                  // 
    input                c,                  // 
    input                en,                 //
    output               y                   // 
    output               w                   // 
);

assign y = 1'b1;              // ERASE
assign w = 1'b1;              // ERASE

endmodule

combinational-logic/multiplexers-and-demultiplexers/jeff-74x151/jeff-74x151-tb.v
`timescale 1ns / 1ns
`include "jeff-74x151.v"

module jeff_74x151_tb;

// DATA TYPES - DECLAIR INPUTS AND OUTPUTS
reg        D0, D1, D2, D3, D4, D5, D6, D7;
reg        A, B, C;
reg        EN;
wire       Y, W;

// UUT
jeff_74x151 uut(
    .d0(D0), .d1(D1), .d2(D2), .d3(D3), .d4(D4), .d5(D5), .d6(D6), .d7(D7),
    .a(A), .b(B), .c(C),
    .en(EN),
    .y(Y), .w(W)
);

// FILES
initial begin
    $dumpfile("jeff-74x151-tb.vcd");
    $dumpvars(0, jeff_74x151_tb);
end

// TESTCASE
initial begin
    $display("test start");
    D7 = 0; D6 = 0; D5 = 0; D4 = 0; D3 = 0; D2 = 0; D1 = 0; D0 = 0;
    C = 0; B = 0; A = 0;
    EN = 0;

    #10; C = 0; B = 0; A = 0;
    #10; D7 = 0; D6 = 0; D5 = 0; D4 = 0; D3 = 0; D2 = 0; D1 = 0; D0 = 1;
    #10; C = 0; B = 0; A = 1;
    #10; D7 = 0; D6 = 0; D5 = 0; D4 = 0; D3 = 0; D2 = 0; D1 = 1; D0 = 0;
    #10; C = 0; B = 1; A = 0;
    #10; D7 = 0; D6 = 0; D5 = 0; D4 = 0; D3 = 0; D2 = 1; D1 = 0; D0 = 0;
    #10; C = 0; B = 1; A = 1;
    #10; D7 = 0; D6 = 0; D5 = 0; D4 = 0; D3 = 1; D2 = 0; D1 = 0; D0 = 0;
    #10; C = 1; B = 0; A = 0;
    #10; D7 = 0; D6 = 0; D5 = 0; D4 = 1; D3 = 0; D2 = 0; D1 = 0; D0 = 0;
    #10; C = 1; B = 0; A = 1;
    #10; D7 = 0; D6 = 0; D5 = 1; D4 = 0; D3 = 0; D2 = 0; D1 = 0; D0 = 0;
    #10; C = 1; B = 1; A = 0;
    #10; D7 = 0; D6 = 1; D5 = 0; D4 = 0; D3 = 0; D2 = 0; D1 = 0; D0 = 0;
    #10; C = 1; B = 1; A = 1;
    #10; D7 = 1; D6 = 0; D5 = 0; D4 = 0; D3 = 0; D2 = 0; D1 = 0; D0 = 0;
    #10

    EN = 1;
    #10

    $display("test complete");
    $finish;
end

endmodule

combinational-logic/multiplexers-and-demultiplexers/jeff-74x151/jeff-74x151-tb.vcd
$date
	Tue Oct 27 09:40:21 2020
$end
$version
	Icarus Verilog
$end
$timescale
	1ns
$end
$scope module jeff_74x151_tb $end
$var wire 1 ! Y $end
$var wire 1 " W $end
$var reg 1 # A $end
$var reg 1 $ B $end
$var reg 1 % C $end
$var reg 1 & D0 $end
$var reg 1 ' D1 $end
$var reg 1 ( D2 $end
$var reg 1 ) D3 $end
$var reg 1 * D4 $end
$var reg 1 + D5 $end
$var reg 1 , D6 $end
$var reg 1 - D7 $end
$var reg 1 . EN $end
$scope module uut $end
$var wire 1 # a $end
$var wire 1 $ b $end
$var wire 1 % c $end
$var wire 1 & d0 $end
$var wire 1 ' d1 $end
$var wire 1 ( d2 $end
$var wire 1 ) d3 $end
$var wire 1 * d4 $end
$var wire 1 + d5 $end
$var wire 1 , d6 $end
$var wire 1 - d7 $end
$var wire 1 . en $end
$var wire 1 " w $end
$var reg 1 ! y $end
$upscope $end
$upscope $end
$enddefinitions $end
#0
$dumpvars
0.
0-
0,
0+
0*
0)
0(
0'
0&
0%
0$
0#
1"
0!
$end
#20
0"
1!
1&
#30
1"
0!
1#
#40
0"
1!
0&
1'
#50
1"
0!
0#
1$
#60
0"
1!
0'
1(
#70
1"
0!
1#
#80
0"
1!
0(
1)
#90
1"
0!
0#
0$
1%
#100
0"
1!
0)
1*
#110
1"
0!
1#
#120
0"
1!
0*
1+
#130
1"
0!
0#
1$
#140
0"
1!
0+
1,
#150
1"
0!
1#
#160
0"
1!
0,
1-
#170
1.
