sequential-logic/counters/jeff_74x161/jeff-74x161.v
// Synchronous presettable 4-bit binary counter, asynchronous clear
module jeff_74x161(
    input        clk,           // Clock
    input        rst,           // Reset
    input        in,            // IN
    output       out            // OUT
);

reg       out;

always @ (posedge clk) begin
    if (rst) begin
        out <= 1'b0;
    end else begin
        out <= in;
    end
end

endmodule

sequential-logic/counters/jeff-74x161/jeff-74x161-tb.v
`timescale 1ns / 1ns
`include "jeff-74x161.v"

module jeff_74x161_tb;

// DATA TYPES - DECLAIR INPUTS AND OUTPUTS
reg        CLK, RST;
reg        IN;
wire       OUT;

// UUT
jeff_74x161 uut(
    .clk(CLK), .rst(RST),
    .in(IN),
    .out(OUT)
);

// FILES
initial begin
    $dumpfile("jeff-74x161-tb.vcd");
    $dumpvars(0, jeff_74x161_tb);
end

// CLOCK
always begin
    #10 CLK = ~CLK;
end

// TESTCASE
initial begin
    $display("test start");
    CLK = 0;
    RST = 0;
    IN = 0;

    #15; RST = 1;
    #20; RST = 0;

    #20; IN = 1;
    #20; IN = 0;
    #20; IN = 1;
    #20; IN = 0;
    #20; IN = 0;
    
    // DONE
    #20

    $display("test complete");
    $finish;
end

endmodule

sequential-logic/counters/jeff_74x161/jeff-74x161-tb.vcd
$date
	Sat Oct 24 05:43:23 2020
$end
$version
	Icarus Verilog
$end
$timescale
	1ns
$end
$scope module jeff_74x161_tb $end
$var wire 1 ! OUT $end
$var reg 1 " CLK $end
$var reg 1 # IN $end
$var reg 1 $ RST $end
$scope module uut $end
$var wire 1 " clk $end
$var wire 1 # in $end
$var wire 1 $ rst $end
$var reg 1 ! out $end
$upscope $end
$upscope $end
$enddefinitions $end
#0
$dumpvars
0$
0#
0"
x!
$end
#10
0!
1"
#15
1$
#20
0"
#30
1"
#35
0$
#40
0"
#50
1"
#55
1#
#60
0"
#70
1!
1"
#75
0#
#80
0"
#90
0!
1"
#95
1#
#100
0"
#110
1!
1"
#115
0#
#120
0"
#130
0!
1"
