basic-code/sequential-logic/sr_flip_flop/sr_flip_flop.v
// A sr (set ready) flip-flop which is pulse-triggered can be set and reset.

module sr_flip_flop_gate (
    input       clk,        // Clock
    input       s,          // Inputs
    input       r,          // 
    output      q,          // Output
    output      qbar);      //

    // INTERNAL WIRES
    wire        s1, r1;
  
    // NAND3
    nand (s1, s, clk);

    // NAND4
    nand (r1, r, clk);

    // SR- LATCH -------------------------------------
    
    // NAND1
    nand (q, s1, qbar);

    // NAND2
    nand (qbar, r1, q);

endmodule

module sr_flip_flop_dataflow (
    input       clk,        // Clock
    input       s,          // Inputs
    input       r,          // 
    output      q,          // Output
    output      qbar);      //

    // INTERNAL WIRES
    wire        s1, r1;
  
    // NAND3
    assign s1 = ~(s & clk);

    // NAND4
    assign r1 = ~(r & clk);

    // SR- LATCH -------------------------------------
    
    // NAND1
    assign q = ~(s1 & qbar);

    // NAND2
    assign qbar = ~(r1 & q);

endmodule

module sr_flip_flop_behavioral (
    input       clk,        // Clock
    input       s,          // Inputs
    input       r,          // 
    output reg  q,          // Output
    output      qbar);      //

    // INTERNAL WIRES
    assign qbar = ~q;

    always @(posedge clk) begin
        case({s,r})
            2'b0_0 : q <= q;
            2'b0_1 : q <= 1'b0;
            2'b1_0 : q <= 1'b1;
            2'b1_1 : q <= 1'bx;
        endcase
    end

endmodule

basic-code/sequential-logic/sr_flip_flop/sr_flip_flop_tb.v
`timescale 1ns / 100ps // time-unit = 1 ns, precision = 100 ps

// include files are in sr_flip_flop.vh

module SR_FLIP_FLOP_TB ();

    // INPUT PROBES
    reg             S, R;

    // OUTPUT PROBES
    wire            Q_gate, QBAR_gate;
    wire            Q_data, QBAR_data;
    wire            Q_beh, QBAR_beh;

    // FOR TESTING  
    reg             CLK;
    reg [31:0]      VECTORCOUNT, ERRORS;
    reg             QEXPECTED;
    integer         FD, COUNT;
    reg [8*32-1:0]  COMMENT;

    // UNIT UNDER TEST (gate)
    sr_flip_flop_gate UUT_sr_flip_flop_gate(
        .clk(CLK),
        .s(S), .r(R),
        .q(Q_gate), .qbar(QBAR_gate)
    );

    // UNIT UNDER TEST (dataflow)
    sr_flip_flop_dataflow UUT_sr_flip_flop_dataflow(
        .clk(CLK),
        .s(S), .r(R),
        .q(Q_data), .qbar(QBAR_data)
    );

        // UNIT UNDER TEST (behavioral)
    sr_flip_flop_behavioral UUT_sr_flip_flop_behavioral(
        .clk(CLK),
        .s(S), .r(R),
        .q(Q_beh), .qbar(QBAR_beh)
    );

    // SAVE EVERYTHING FROM TOP TB MODULE IN A DUMP FILE
    initial begin
        $dumpfile("sr_flip_flop_tb.vcd");
        $dumpvars(0, SR_FLIP_FLOP_TB);
    end

    // CLK PERIOD
    localparam CLKPERIOD = 20;

    // CLK
    always begin
        #(CLKPERIOD/2) CLK = ~CLK;
    end

    // INITIALIZE TESTBENCH
    initial begin

        // OPEN VECTOR FILE - THROW AWAY FIRST LINE
        FD=$fopen("sr_flip_flop_tb.tv","r");
        COUNT = $fscanf(FD, "%s", COMMENT);
        // $display ("FIRST LINE IS: %s", COMMENT);

        // INIT TESTBENCH
        COUNT = $fscanf(FD, "%s %b %b %b", COMMENT, S, R, QEXPECTED);
        CLK = 0;
        VECTORCOUNT = 1;
        ERRORS = 0;

        // DISPAY OUTPUT AND MONITOR
        $display();
        $display("TEST START --------------------------------");
        $display();
        $display("                                     GATE  DATA   BEH");
        $display("                 | TIME(ns) | S | R |  Q  |  Q  |  Q  |");
        $display("                 --------------------------------------");
        // $monitor("%4d  %10s | %8d | %1d | %1d |  %1d  |  %1d  |  %1d  |", VECTORCOUNT, COMMENT, $time, S, R, Q_gate, Q_data, Q_beh);

    end

    // APPLY TEST VECTORS ON NEG EDGE CLK (ADD DELAY)
    always @(negedge CLK) begin

        // WAIT A BIT (AFTER CHECK)
        #5;

        // GET VECTORS FROM TB FILE
        COUNT = $fscanf(FD, "%s %b %b %b", COMMENT, S, R, QEXPECTED);

        // CHECK IF EOF - PRINT SUMMARY, CLOSE VECTOR FILE AND FINISH TB
        if (COUNT == -1) begin
            $fclose(FD);
            $display();
            $display(" VECTORS: %4d", VECTORCOUNT);
            $display("  ERRORS: %4d", ERRORS);
            $display();
            $display("TEST END ----------------------------------");
            $display();
            $finish;
        end

        // GET ANOTHER VECTOR
        VECTORCOUNT = VECTORCOUNT + 1;

    end

    // CHECK TEST VECTORS ON POS EGDE CLK
    always @(posedge CLK) begin

        // WAIT A BIT
        #5;

        // DISPLAY OUTPUT ON POS EDGE CLK
        $display("%4d  %10s | %8d | %1d | %1d |  %1d  |  %1d  |  %1d  |", VECTORCOUNT, COMMENT, $time, S, R, Q_gate, Q_data, Q_beh);

        // CHECK EACH VECTOR RESULT
        if (Q_gate !== QEXPECTED) begin
            $display("***ERROR (gate) - Expected Q = %b", QEXPECTED);
            ERRORS = ERRORS + 1;
        end
        if (Q_data !== QEXPECTED) begin
            $display("***ERROR (dataflow) - Expected Q = %b", QEXPECTED);
            ERRORS = ERRORS + 1;
        end
        if (Q_beh !== QEXPECTED) begin
            $display("***ERROR (behavioral) - Expected Q = %b", QEXPECTED);
            ERRORS = ERRORS + 1;
        end

    end   

endmodule

basic-code/sequential-logic/sr_flip_flop/sr_flip_flop_tb.vcd
$date
	Sun Apr 30 22:40:23 2023
$end
$version
	Icarus Verilog
$end
$timescale
	100ps
$end
$scope module SR_FLIP_FLOP_TB $end
$var wire 1 ! Q_gate $end
$var wire 1 " Q_data $end
$var wire 1 # Q_beh $end
$var wire 1 $ QBAR_gate $end
$var wire 1 % QBAR_data $end
$var wire 1 & QBAR_beh $end
$var parameter 32 ' CLKPERIOD $end
$var reg 1 ( CLK $end
$var reg 256 ) COMMENT [255:0] $end
$var reg 32 * ERRORS [31:0] $end
$var reg 1 + QEXPECTED $end
$var reg 1 , R $end
$var reg 1 - S $end
$var reg 32 . VECTORCOUNT [31:0] $end
$var integer 32 / COUNT [31:0] $end
$var integer 32 0 FD [31:0] $end
$scope module UUT_sr_flip_flop_behavioral $end
$var wire 1 ( clk $end
$var wire 1 & qbar $end
$var wire 1 , r $end
$var wire 1 - s $end
$var reg 1 # q $end
$upscope $end
$scope module UUT_sr_flip_flop_dataflow $end
$var wire 1 ( clk $end
$var wire 1 " q $end
$var wire 1 % qbar $end
$var wire 1 , r $end
$var wire 1 1 r1 $end
$var wire 1 - s $end
$var wire 1 2 s1 $end
$upscope $end
$scope module UUT_sr_flip_flop_gate $end
$var wire 1 ( clk $end
$var wire 1 ! q $end
$var wire 1 $ qbar $end
$var wire 1 , r $end
$var wire 1 3 r1 $end
$var wire 1 - s $end
$var wire 1 4 s1 $end
$upscope $end
$upscope $end
$enddefinitions $end
$comment Show the parameter values. $end
$dumpall
b10100 '
$end
#0
$dumpvars
14
13
12
11
b10000000000000000000000000000011 0
b100 /
b0 .
0-
0,
x+
b0 *
b0 )
0(
x&
x%
x$
x#
x"
x!
$end
#100
1(
#200
0(
#250
b1 .
1+
1-
b10100110100010101010100 )
#300
0&
1#
0%
1"
0$
02
1!
04
1(
#400
12
14
0(
#450
b10 .
0-
b10011100100111101011111010000110100100001000001010011100100011101000101 )
#500
1(
#600
0(
#650
b11 .
0+
1,
b101001001000101010100110100010101010100 )
#700
1&
0#
0"
1%
0!
01
1$
03
1(
#800
11
13
0(
#850
b100 .
0,
b10011100100111101011111010000110100100001000001010011100100011101000101 )
#900
1(
#1000
0(
#1050
b101 .
1+
1-
b10100110100010101010100 )
#1100
0&
1#
0%
1"
0$
02
1!
04
1(
#1200
12
14
0(
#1250
b110 .
0-
b10011100100111101011111010000110100100001000001010011100100011101000101 )
#1300
1(
#1400
0(
#1450
b111 .
0+
1,
b101001001000101010100110100010101010100 )
#1500
1&
0#
0"
1%
0!
01
1$
03
1(
#1600
11
13
0(
#1650
b1000 .
0,
b10011100100111101011111010000110100100001000001010011100100011101000101 )
#1700
1(
#1800
0(
#1850
b11111111111111111111111111111111 /
